{
  "sample_id": "sample_0415_20250530_152323_376",
  "timestamp": "20250530_152323_376",
  "sample_count": 415,
  "session_start": "2025-05-30T15:22:04.397580",
  "camera_info": {
    "width": 640,
    "height": 480,
    "depth_scale": 0.0010000000474974513,
    "origin_x": 320,
    "origin_y": 240
  },
  "files": {
    "color_image": "sample_0415_20250530_152323_376.jpg",
    "depth_data": "sample_0415_20250530_152323_376_depth.npy"
  },
  "detections": [
    {
      "detection_id": 0,
      "class_id": 1,
      "confidence": 0.8442316055297852,
      "bounding_box": {
        "x1": 193,
        "y1": 464,
        "x2": 203,
        "y2": 478,
        "center_x": 198,
        "center_y": 471,
        "width": 10,
        "height": 14
      },
      "relative_coordinates": {
        "rel_x": -122.0,
        "rel_y": 231.0
      },
      "depth_information": {
        "statistics": {
          "mean_depth": 5.209400247433223,
          "median_depth": 5.1790002459893,
          "min_depth": 4.778000226942822,
          "max_depth": 5.926000281469896,
          "std_depth": 0.2873921250840327,
          "valid_pixels": 140,
          "total_pixels": 140,
          "fill_ratio": 1.0
        },
        "realsense_depth_data": {
          "center_point": {
            "pixel_x": 198,
            "pixel_y": 471,
            "depth_raw": 5136,
            "depth_meters": 5.13600024394691
          },
          "sample_points": [
            {
              "pixel_x": 193,
              "pixel_y": 464,
              "depth_raw": 5926,
              "depth_meters": 5.926000281469896
            },
            {
              "pixel_x": 194,
              "pixel_y": 464,
              "depth_raw": 5814,
              "depth_meters": 5.814000276150182
            },
            {
              "pixel_x": 195,
              "pixel_y": 464,
              "depth_raw": 5814,
              "depth_meters": 5.814000276150182
            },
            {
              "pixel_x": 196,
              "pixel_y": 464,
              "depth_raw": 5707,
              "depth_meters": 5.707000271067955
            },
            {
              "pixel_x": 197,
              "pixel_y": 464,
              "depth_raw": 5707,
              "depth_meters": 5.707000271067955
            },
            {
              "pixel_x": 198,
              "pixel_y": 464,
              "depth_raw": 5707,
              "depth_meters": 5.707000271067955
            },
            {
              "pixel_x": 199,
              "pixel_y": 464,
              "depth_raw": 5654,
              "depth_meters": 5.65400026855059
            },
            {
              "pixel_x": 200,
              "pixel_y": 464,
              "depth_raw": 5654,
              "depth_meters": 5.65400026855059
            },
            {
              "pixel_x": 201,
              "pixel_y": 464,
              "depth_raw": 5603,
              "depth_meters": 5.60300026612822
            },
            {
              "pixel_x": 202,
              "pixel_y": 464,
              "depth_raw": 5603,
              "depth_meters": 5.60300026612822
            },
            {
              "pixel_x": 193,
              "pixel_y": 465,
              "depth_raw": 5814,
              "depth_meters": 5.814000276150182
            },
            {
              "pixel_x": 194,
              "pixel_y": 465,
              "depth_raw": 5603,
              "depth_meters": 5.60300026612822
            },
            {
              "pixel_x": 195,
              "pixel_y": 465,
              "depth_raw": 5603,
              "depth_meters": 5.60300026612822
            },
            {
              "pixel_x": 196,
              "pixel_y": 465,
              "depth_raw": 5552,
              "depth_meters": 5.55200026370585
            },
            {
              "pixel_x": 197,
              "pixel_y": 465,
              "depth_raw": 5552,
              "depth_meters": 5.55200026370585
            },
            {
              "pixel_x": 198,
              "pixel_y": 465,
              "depth_raw": 5552,
              "depth_meters": 5.55200026370585
            },
            {
              "pixel_x": 199,
              "pixel_y": 465,
              "depth_raw": 5503,
              "depth_meters": 5.5030002613784745
            },
            {
              "pixel_x": 200,
              "pixel_y": 465,
              "depth_raw": 5503,
              "depth_meters": 5.5030002613784745
            },
            {
              "pixel_x": 201,
              "pixel_y": 465,
              "depth_raw": 5454,
              "depth_meters": 5.454000259051099
            },
            {
              "pixel_x": 202,
              "pixel_y": 465,
              "depth_raw": 5406,
              "depth_meters": 5.406000256771222
            },
            {
              "pixel_x": 193,
              "pixel_y": 466,
              "depth_raw": 5814,
              "depth_meters": 5.814000276150182
            },
            {
              "pixel_x": 194,
              "pixel_y": 466,
              "depth_raw": 5603,
              "depth_meters": 5.60300026612822
            },
            {
              "pixel_x": 195,
              "pixel_y": 466,
              "depth_raw": 5603,
              "depth_meters": 5.60300026612822
            },
            {
              "pixel_x": 196,
              "pixel_y": 466,
              "depth_raw": 5552,
              "depth_meters": 5.55200026370585
            },
            {
              "pixel_x": 197,
              "pixel_y": 466,
              "depth_raw": 5552,
              "depth_meters": 5.55200026370585
            },
            {
              "pixel_x": 198,
              "pixel_y": 466,
              "depth_raw": 5552,
              "depth_meters": 5.55200026370585
            },
            {
              "pixel_x": 199,
              "pixel_y": 466,
              "depth_raw": 5503,
              "depth_meters": 5.5030002613784745
            },
            {
              "pixel_x": 200,
              "pixel_y": 466,
              "depth_raw": 5503,
              "depth_meters": 5.5030002613784745
            },
            {
              "pixel_x": 201,
              "pixel_y": 466,
              "depth_raw": 5454,
              "depth_meters": 5.454000259051099
            },
            {
              "pixel_x": 202,
              "pixel_y": 466,
              "depth_raw": 5406,
              "depth_meters": 5.406000256771222
            },
            {
              "pixel_x": 193,
              "pixel_y": 467,
              "depth_raw": 5654,
              "depth_meters": 5.65400026855059
            },
            {
              "pixel_x": 194,
              "pixel_y": 467,
              "depth_raw": 5503,
              "depth_meters": 5.5030002613784745
            },
            {
              "pixel_x": 195,
              "pixel_y": 467,
              "depth_raw": 5503,
              "depth_meters": 5.5030002613784745
            },
            {
              "pixel_x": 196,
              "pixel_y": 467,
              "depth_raw": 5406,
              "depth_meters": 5.406000256771222
            },
            {
              "pixel_x": 197,
              "pixel_y": 467,
              "depth_raw": 5406,
              "depth_meters": 5.406000256771222
            },
            {
              "pixel_x": 198,
              "pixel_y": 467,
              "depth_raw": 5359,
              "depth_meters": 5.3590002545388415
            },
            {
              "pixel_x": 199,
              "pixel_y": 467,
              "depth_raw": 5359,
              "depth_meters": 5.3590002545388415
            },
            {
              "pixel_x": 200,
              "pixel_y": 467,
              "depth_raw": 5359,
              "depth_meters": 5.3590002545388415
            },
            {
              "pixel_x": 201,
              "pixel_y": 467,
              "depth_raw": 5313,
              "depth_meters": 5.313000252353959
            },
            {
              "pixel_x": 202,
              "pixel_y": 467,
              "depth_raw": 5268,
              "depth_meters": 5.2680002502165735
            },
            {
              "pixel_x": 193,
              "pixel_y": 468,
              "depth_raw": 5503,
              "depth_meters": 5.5030002613784745
            },
            {
              "pixel_x": 194,
              "pixel_y": 468,
              "depth_raw": 5503,
              "depth_meters": 5.5030002613784745
            },
            {
              "pixel_x": 195,
              "pixel_y": 468,
              "depth_raw": 5359,
              "depth_meters": 5.3590002545388415
            },
            {
              "pixel_x": 196,
              "pixel_y": 468,
              "depth_raw": 5268,
              "depth_meters": 5.2680002502165735
            },
            {
              "pixel_x": 197,
              "pixel_y": 468,
              "depth_raw": 5268,
              "depth_meters": 5.2680002502165735
            },
            {
              "pixel_x": 198,
              "pixel_y": 468,
              "depth_raw": 5268,
              "depth_meters": 5.2680002502165735
            },
            {
              "pixel_x": 199,
              "pixel_y": 468,
              "depth_raw": 5223,
              "depth_meters": 5.223000248079188
            },
            {
              "pixel_x": 200,
              "pixel_y": 468,
              "depth_raw": 5223,
              "depth_meters": 5.223000248079188
            },
            {
              "pixel_x": 201,
              "pixel_y": 468,
              "depth_raw": 5179,
              "depth_meters": 5.1790002459893
            },
            {
              "pixel_x": 202,
              "pixel_y": 468,
              "depth_raw": 5136,
              "depth_meters": 5.13600024394691
            },
            {
              "pixel_x": 193,
              "pixel_y": 469,
              "depth_raw": 5503,
              "depth_meters": 5.5030002613784745
            },
            {
              "pixel_x": 194,
              "pixel_y": 469,
              "depth_raw": 5503,
              "depth_meters": 5.5030002613784745
            },
            {
              "pixel_x": 195,
              "pixel_y": 469,
              "depth_raw": 5359,
              "depth_meters": 5.3590002545388415
            },
            {
              "pixel_x": 196,
              "pixel_y": 469,
              "depth_raw": 5268,
              "depth_meters": 5.2680002502165735
            },
            {
              "pixel_x": 197,
              "pixel_y": 469,
              "depth_raw": 5268,
              "depth_meters": 5.2680002502165735
            },
            {
              "pixel_x": 198,
              "pixel_y": 469,
              "depth_raw": 5268,
              "depth_meters": 5.2680002502165735
            },
            {
              "pixel_x": 199,
              "pixel_y": 469,
              "depth_raw": 5223,
              "depth_meters": 5.223000248079188
            },
            {
              "pixel_x": 200,
              "pixel_y": 469,
              "depth_raw": 5223,
              "depth_meters": 5.223000248079188
            },
            {
              "pixel_x": 201,
              "pixel_y": 469,
              "depth_raw": 5179,
              "depth_meters": 5.1790002459893
            },
            {
              "pixel_x": 202,
              "pixel_y": 469,
              "depth_raw": 5136,
              "depth_meters": 5.13600024394691
            },
            {
              "pixel_x": 193,
              "pixel_y": 470,
              "depth_raw": 5406,
              "depth_meters": 5.406000256771222
            },
            {
              "pixel_x": 194,
              "pixel_y": 470,
              "depth_raw": 5406,
              "depth_meters": 5.406000256771222
            },
            {
              "pixel_x": 195,
              "pixel_y": 470,
              "depth_raw": 5223,
              "depth_meters": 5.223000248079188
            },
            {
              "pixel_x": 196,
              "pixel_y": 470,
              "depth_raw": 5136,
              "depth_meters": 5.13600024394691
            },
            {
              "pixel_x": 197,
              "pixel_y": 470,
              "depth_raw": 5136,
              "depth_meters": 5.13600024394691
            },
            {
              "pixel_x": 198,
              "pixel_y": 470,
              "depth_raw": 5136,
              "depth_meters": 5.13600024394691
            },
            {
              "pixel_x": 199,
              "pixel_y": 470,
              "depth_raw": 5094,
              "depth_meters": 5.094000241952017
            },
            {
              "pixel_x": 200,
              "pixel_y": 470,
              "depth_raw": 5094,
              "depth_meters": 5.094000241952017
            },
            {
              "pixel_x": 201,
              "pixel_y": 470,
              "depth_raw": 5052,
              "depth_meters": 5.052000239957124
            },
            {
              "pixel_x": 202,
              "pixel_y": 470,
              "depth_raw": 5052,
              "depth_meters": 5.052000239957124
            },
            {
              "pixel_x": 193,
              "pixel_y": 471,
              "depth_raw": 5406,
              "depth_meters": 5.406000256771222
            },
            {
              "pixel_x": 194,
              "pixel_y": 471,
              "depth_raw": 5406,
              "depth_meters": 5.406000256771222
            },
            {
              "pixel_x": 195,
              "pixel_y": 471,
              "depth_raw": 5223,
              "depth_meters": 5.223000248079188
            },
            {
              "pixel_x": 196,
              "pixel_y": 471,
              "depth_raw": 5136,
              "depth_meters": 5.13600024394691
            },
            {
              "pixel_x": 197,
              "pixel_y": 471,
              "depth_raw": 5136,
              "depth_meters": 5.13600024394691
            },
            {
              "pixel_x": 198,
              "pixel_y": 471,
              "depth_raw": 5136,
              "depth_meters": 5.13600024394691
            },
            {
              "pixel_x": 199,
              "pixel_y": 471,
              "depth_raw": 5094,
              "depth_meters": 5.094000241952017
            },
            {
              "pixel_x": 200,
              "pixel_y": 471,
              "depth_raw": 5094,
              "depth_meters": 5.094000241952017
            },
            {
              "pixel_x": 201,
              "pixel_y": 471,
              "depth_raw": 4931,
              "depth_meters": 4.931000234209932
            },
            {
              "pixel_x": 202,
              "pixel_y": 471,
              "depth_raw": 4931,
              "depth_meters": 4.931000234209932
            },
            {
              "pixel_x": 193,
              "pixel_y": 472,
              "depth_raw": 5313,
              "depth_meters": 5.313000252353959
            },
            {
              "pixel_x": 194,
              "pixel_y": 472,
              "depth_raw": 5313,
              "depth_meters": 5.313000252353959
            },
            {
              "pixel_x": 195,
              "pixel_y": 472,
              "depth_raw": 5136,
              "depth_meters": 5.13600024394691
            },
            {
              "pixel_x": 196,
              "pixel_y": 472,
              "depth_raw": 5052,
              "depth_meters": 5.052000239957124
            },
            {
              "pixel_x": 197,
              "pixel_y": 472,
              "depth_raw": 5052,
              "depth_meters": 5.052000239957124
            },
            {
              "pixel_x": 198,
              "pixel_y": 472,
              "depth_raw": 5011,
              "depth_meters": 5.0110002380097285
            },
            {
              "pixel_x": 199,
              "pixel_y": 472,
              "depth_raw": 4970,
              "depth_meters": 4.970000236062333
            },
            {
              "pixel_x": 200,
              "pixel_y": 472,
              "depth_raw": 4970,
              "depth_meters": 4.970000236062333
            },
            {
              "pixel_x": 201,
              "pixel_y": 472,
              "depth_raw": 4931,
              "depth_meters": 4.931000234209932
            },
            {
              "pixel_x": 202,
              "pixel_y": 472,
              "depth_raw": 4931,
              "depth_meters": 4.931000234209932
            },
            {
              "pixel_x": 193,
              "pixel_y": 473,
              "depth_raw": 5223,
              "depth_meters": 5.223000248079188
            },
            {
              "pixel_x": 194,
              "pixel_y": 473,
              "depth_raw": 5223,
              "depth_meters": 5.223000248079188
            },
            {
              "pixel_x": 195,
              "pixel_y": 473,
              "depth_raw": 5052,
              "depth_meters": 5.052000239957124
            },
            {
              "pixel_x": 196,
              "pixel_y": 473,
              "depth_raw": 4970,
              "depth_meters": 4.970000236062333
            },
            {
              "pixel_x": 197,
              "pixel_y": 473,
              "depth_raw": 4970,
              "depth_meters": 4.970000236062333
            },
            {
              "pixel_x": 198,
              "pixel_y": 473,
              "depth_raw": 4891,
              "depth_meters": 4.891000232310034
            },
            {
              "pixel_x": 199,
              "pixel_y": 473,
              "depth_raw": 4891,
              "depth_meters": 4.891000232310034
            },
            {
              "pixel_x": 200,
              "pixel_y": 473,
              "depth_raw": 4891,
              "depth_meters": 4.891000232310034
            },
            {
              "pixel_x": 201,
              "pixel_y": 473,
              "depth_raw": 4853,
              "depth_meters": 4.853000230505131
            },
            {
              "pixel_x": 202,
              "pixel_y": 473,
              "depth_raw": 4853,
              "depth_meters": 4.853000230505131
            },
            {
              "pixel_x": 193,
              "pixel_y": 474,
              "depth_raw": 5223,
              "depth_meters": 5.223000248079188
            },
            {
              "pixel_x": 194,
              "pixel_y": 474,
              "depth_raw": 5223,
              "depth_meters": 5.223000248079188
            },
            {
              "pixel_x": 195,
              "pixel_y": 474,
              "depth_raw": 5052,
              "depth_meters": 5.052000239957124
            },
            {
              "pixel_x": 196,
              "pixel_y": 474,
              "depth_raw": 4970,
              "depth_meters": 4.970000236062333
            },
            {
              "pixel_x": 197,
              "pixel_y": 474,
              "depth_raw": 4970,
              "depth_meters": 4.970000236062333
            },
            {
              "pixel_x": 198,
              "pixel_y": 474,
              "depth_raw": 4891,
              "depth_meters": 4.891000232310034
            },
            {
              "pixel_x": 199,
              "pixel_y": 474,
              "depth_raw": 4891,
              "depth_meters": 4.891000232310034
            },
            {
              "pixel_x": 200,
              "pixel_y": 474,
              "depth_raw": 4891,
              "depth_meters": 4.891000232310034
            },
            {
              "pixel_x": 201,
              "pixel_y": 474,
              "depth_raw": 4853,
              "depth_meters": 4.853000230505131
            },
            {
              "pixel_x": 202,
              "pixel_y": 474,
              "depth_raw": 4853,
              "depth_meters": 4.853000230505131
            },
            {
              "pixel_x": 193,
              "pixel_y": 475,
              "depth_raw": 5179,
              "depth_meters": 5.1790002459893
            },
            {
              "pixel_x": 194,
              "pixel_y": 475,
              "depth_raw": 5179,
              "depth_meters": 5.1790002459893
            },
            {
              "pixel_x": 195,
              "pixel_y": 475,
              "depth_raw": 5011,
              "depth_meters": 5.0110002380097285
            },
            {
              "pixel_x": 196,
              "pixel_y": 475,
              "depth_raw": 4891,
              "depth_meters": 4.891000232310034
            },
            {
              "pixel_x": 197,
              "pixel_y": 475,
              "depth_raw": 4891,
              "depth_meters": 4.891000232310034
            },
            {
              "pixel_x": 198,
              "pixel_y": 475,
              "depth_raw": 4853,
              "depth_meters": 4.853000230505131
            },
            {
              "pixel_x": 199,
              "pixel_y": 475,
              "depth_raw": 4853,
              "depth_meters": 4.853000230505131
            },
            {
              "pixel_x": 200,
              "pixel_y": 475,
              "depth_raw": 4815,
              "depth_meters": 4.815000228700228
            },
            {
              "pixel_x": 201,
              "pixel_y": 475,
              "depth_raw": 4778,
              "depth_meters": 4.778000226942822
            },
            {
              "pixel_x": 202,
              "pixel_y": 475,
              "depth_raw": 4778,
              "depth_meters": 4.778000226942822
            },
            {
              "pixel_x": 193,
              "pixel_y": 476,
              "depth_raw": 5136,
              "depth_meters": 5.13600024394691
            },
            {
              "pixel_x": 194,
              "pixel_y": 476,
              "depth_raw": 5136,
              "depth_meters": 5.13600024394691
            },
            {
              "pixel_x": 195,
              "pixel_y": 476,
              "depth_raw": 5011,
              "depth_meters": 5.0110002380097285
            },
            {
              "pixel_x": 196,
              "pixel_y": 476,
              "depth_raw": 4891,
              "depth_meters": 4.891000232310034
            },
            {
              "pixel_x": 197,
              "pixel_y": 476,
              "depth_raw": 4891,
              "depth_meters": 4.891000232310034
            },
            {
              "pixel_x": 198,
              "pixel_y": 476,
              "depth_raw": 4853,
              "depth_meters": 4.853000230505131
            },
            {
              "pixel_x": 199,
              "pixel_y": 476,
              "depth_raw": 4853,
              "depth_meters": 4.853000230505131
            },
            {
              "pixel_x": 200,
              "pixel_y": 476,
              "depth_raw": 4815,
              "depth_meters": 4.815000228700228
            },
            {
              "pixel_x": 201,
              "pixel_y": 476,
              "depth_raw": 4778,
              "depth_meters": 4.778000226942822
            },
            {
              "pixel_x": 202,
              "pixel_y": 476,
              "depth_raw": 4778,
              "depth_meters": 4.778000226942822
            },
            {
              "pixel_x": 193,
              "pixel_y": 477,
              "depth_raw": 5136,
              "depth_meters": 5.13600024394691
            },
            {
              "pixel_x": 194,
              "pixel_y": 477,
              "depth_raw": 5136,
              "depth_meters": 5.13600024394691
            },
            {
              "pixel_x": 195,
              "pixel_y": 477,
              "depth_raw": 5011,
              "depth_meters": 5.0110002380097285
            },
            {
              "pixel_x": 196,
              "pixel_y": 477,
              "depth_raw": 4891,
              "depth_meters": 4.891000232310034
            },
            {
              "pixel_x": 197,
              "pixel_y": 477,
              "depth_raw": 4891,
              "depth_meters": 4.891000232310034
            },
            {
              "pixel_x": 198,
              "pixel_y": 477,
              "depth_raw": 4853,
              "depth_meters": 4.853000230505131
            },
            {
              "pixel_x": 199,
              "pixel_y": 477,
              "depth_raw": 4853,
              "depth_meters": 4.853000230505131
            },
            {
              "pixel_x": 200,
              "pixel_y": 477,
              "depth_raw": 4815,
              "depth_meters": 4.815000228700228
            },
            {
              "pixel_x": 201,
              "pixel_y": 477,
              "depth_raw": 4778,
              "depth_meters": 4.778000226942822
            },
            {
              "pixel_x": 202,
              "pixel_y": 477,
              "depth_raw": 4778,
              "depth_meters": 4.778000226942822
            }
          ],
          "depth_scale_used": 0.0010000000474974513,
          "bounding_box_depth": {
            "roi_shape": [
              14,
              10
            ],
            "mean_raw": 5209.4,
            "median_raw": 5179.0
          }
        }
      }
    },
    {
      "detection_id": 1,
      "class_id": 0,
      "confidence": 0.8216060996055603,
      "bounding_box": {
        "x1": 212,
        "y1": 464,
        "x2": 222,
        "y2": 478,
        "center_x": 217,
        "center_y": 471,
        "width": 10,
        "height": 14
      },
      "relative_coordinates": {
        "rel_x": -103.0,
        "rel_y": 231.0
      },
      "depth_information": {
        "statistics": {
          "mean_depth": 4.889835946540448,
          "median_depth": 4.815000228700228,
          "min_depth": 4.565000216825865,
          "max_depth": 5.406000256771222,
          "std_depth": 0.23851295229885192,
          "valid_pixels": 140,
          "total_pixels": 140,
          "fill_ratio": 1.0
        },
        "realsense_depth_data": {
          "center_point": {
            "pixel_x": 217,
            "pixel_y": 471,
            "depth_raw": 4741,
            "depth_meters": 4.741000225185417
          },
          "sample_points": [
            {
              "pixel_x": 212,
              "pixel_y": 464,
              "depth_raw": 5406,
              "depth_meters": 5.406000256771222
            },
            {
              "pixel_x": 213,
              "pixel_y": 464,
              "depth_raw": 5359,
              "depth_meters": 5.3590002545388415
            },
            {
              "pixel_x": 214,
              "pixel_y": 464,
              "depth_raw": 5359,
              "depth_meters": 5.3590002545388415
            },
            {
              "pixel_x": 215,
              "pixel_y": 464,
              "depth_raw": 5359,
              "depth_meters": 5.3590002545388415
            },
            {
              "pixel_x": 216,
              "pixel_y": 464,
              "depth_raw": 5359,
              "depth_meters": 5.3590002545388415
            },
            {
              "pixel_x": 217,
              "pixel_y": 464,
              "depth_raw": 5359,
              "depth_meters": 5.3590002545388415
            },
            {
              "pixel_x": 218,
              "pixel_y": 464,
              "depth_raw": 5359,
              "depth_meters": 5.3590002545388415
            },
            {
              "pixel_x": 219,
              "pixel_y": 464,
              "depth_raw": 5359,
              "depth_meters": 5.3590002545388415
            },
            {
              "pixel_x": 220,
              "pixel_y": 464,
              "depth_raw": 5359,
              "depth_meters": 5.3590002545388415
            },
            {
              "pixel_x": 221,
              "pixel_y": 464,
              "depth_raw": 5359,
              "depth_meters": 5.3590002545388415
            },
            {
              "pixel_x": 212,
              "pixel_y": 465,
              "depth_raw": 5268,
              "depth_meters": 5.2680002502165735
            },
            {
              "pixel_x": 213,
              "pixel_y": 465,
              "depth_raw": 5223,
              "depth_meters": 5.223000248079188
            },
            {
              "pixel_x": 214,
              "pixel_y": 465,
              "depth_raw": 5223,
              "depth_meters": 5.223000248079188
            },
            {
              "pixel_x": 215,
              "pixel_y": 465,
              "depth_raw": 5223,
              "depth_meters": 5.223000248079188
            },
            {
              "pixel_x": 216,
              "pixel_y": 465,
              "depth_raw": 5223,
              "depth_meters": 5.223000248079188
            },
            {
              "pixel_x": 217,
              "pixel_y": 465,
              "depth_raw": 5223,
              "depth_meters": 5.223000248079188
            },
            {
              "pixel_x": 218,
              "pixel_y": 465,
              "depth_raw": 5223,
              "depth_meters": 5.223000248079188
            },
            {
              "pixel_x": 219,
              "pixel_y": 465,
              "depth_raw": 5223,
              "depth_meters": 5.223000248079188
            },
            {
              "pixel_x": 220,
              "pixel_y": 465,
              "depth_raw": 5223,
              "depth_meters": 5.223000248079188
            },
            {
              "pixel_x": 221,
              "pixel_y": 465,
              "depth_raw": 5268,
              "depth_meters": 5.2680002502165735
            },
            {
              "pixel_x": 212,
              "pixel_y": 466,
              "depth_raw": 5268,
              "depth_meters": 5.2680002502165735
            },
            {
              "pixel_x": 213,
              "pixel_y": 466,
              "depth_raw": 5223,
              "depth_meters": 5.223000248079188
            },
            {
              "pixel_x": 214,
              "pixel_y": 466,
              "depth_raw": 5223,
              "depth_meters": 5.223000248079188
            },
            {
              "pixel_x": 215,
              "pixel_y": 466,
              "depth_raw": 5052,
              "depth_meters": 5.052000239957124
            },
            {
              "pixel_x": 216,
              "pixel_y": 466,
              "depth_raw": 5052,
              "depth_meters": 5.052000239957124
            },
            {
              "pixel_x": 217,
              "pixel_y": 466,
              "depth_raw": 5052,
              "depth_meters": 5.052000239957124
            },
            {
              "pixel_x": 218,
              "pixel_y": 466,
              "depth_raw": 5094,
              "depth_meters": 5.094000241952017
            },
            {
              "pixel_x": 219,
              "pixel_y": 466,
              "depth_raw": 5136,
              "depth_meters": 5.13600024394691
            },
            {
              "pixel_x": 220,
              "pixel_y": 466,
              "depth_raw": 5136,
              "depth_meters": 5.13600024394691
            },
            {
              "pixel_x": 221,
              "pixel_y": 466,
              "depth_raw": 5136,
              "depth_meters": 5.13600024394691
            },
            {
              "pixel_x": 212,
              "pixel_y": 467,
              "depth_raw": 5094,
              "depth_meters": 5.094000241952017
            },
            {
              "pixel_x": 213,
              "pixel_y": 467,
              "depth_raw": 5094,
              "depth_meters": 5.094000241952017
            },
            {
              "pixel_x": 214,
              "pixel_y": 467,
              "depth_raw": 5094,
              "depth_meters": 5.094000241952017
            },
            {
              "pixel_x": 215,
              "pixel_y": 467,
              "depth_raw": 5052,
              "depth_meters": 5.052000239957124
            },
            {
              "pixel_x": 216,
              "pixel_y": 467,
              "depth_raw": 5052,
              "depth_meters": 5.052000239957124
            },
            {
              "pixel_x": 217,
              "pixel_y": 467,
              "depth_raw": 5052,
              "depth_meters": 5.052000239957124
            },
            {
              "pixel_x": 218,
              "pixel_y": 467,
              "depth_raw": 5094,
              "depth_meters": 5.094000241952017
            },
            {
              "pixel_x": 219,
              "pixel_y": 467,
              "depth_raw": 5136,
              "depth_meters": 5.13600024394691
            },
            {
              "pixel_x": 220,
              "pixel_y": 467,
              "depth_raw": 5136,
              "depth_meters": 5.13600024394691
            },
            {
              "pixel_x": 221,
              "pixel_y": 467,
              "depth_raw": 5136,
              "depth_meters": 5.13600024394691
            },
            {
              "pixel_x": 212,
              "pixel_y": 468,
              "depth_raw": 4970,
              "depth_meters": 4.970000236062333
            },
            {
              "pixel_x": 213,
              "pixel_y": 468,
              "depth_raw": 4970,
              "depth_meters": 4.970000236062333
            },
            {
              "pixel_x": 214,
              "pixel_y": 468,
              "depth_raw": 4931,
              "depth_meters": 4.931000234209932
            },
            {
              "pixel_x": 215,
              "pixel_y": 468,
              "depth_raw": 4931,
              "depth_meters": 4.931000234209932
            },
            {
              "pixel_x": 216,
              "pixel_y": 468,
              "depth_raw": 4931,
              "depth_meters": 4.931000234209932
            },
            {
              "pixel_x": 217,
              "pixel_y": 468,
              "depth_raw": 4931,
              "depth_meters": 4.931000234209932
            },
            {
              "pixel_x": 218,
              "pixel_y": 468,
              "depth_raw": 4970,
              "depth_meters": 4.970000236062333
            },
            {
              "pixel_x": 219,
              "pixel_y": 468,
              "depth_raw": 5011,
              "depth_meters": 5.0110002380097285
            },
            {
              "pixel_x": 220,
              "pixel_y": 468,
              "depth_raw": 5011,
              "depth_meters": 5.0110002380097285
            },
            {
              "pixel_x": 221,
              "pixel_y": 468,
              "depth_raw": 5052,
              "depth_meters": 5.052000239957124
            },
            {
              "pixel_x": 212,
              "pixel_y": 469,
              "depth_raw": 4970,
              "depth_meters": 4.970000236062333
            },
            {
              "pixel_x": 213,
              "pixel_y": 469,
              "depth_raw": 4970,
              "depth_meters": 4.970000236062333
            },
            {
              "pixel_x": 214,
              "pixel_y": 469,
              "depth_raw": 4931,
              "depth_meters": 4.931000234209932
            },
            {
              "pixel_x": 215,
              "pixel_y": 469,
              "depth_raw": 4931,
              "depth_meters": 4.931000234209932
            },
            {
              "pixel_x": 216,
              "pixel_y": 469,
              "depth_raw": 4931,
              "depth_meters": 4.931000234209932
            },
            {
              "pixel_x": 217,
              "pixel_y": 469,
              "depth_raw": 4931,
              "depth_meters": 4.931000234209932
            },
            {
              "pixel_x": 218,
              "pixel_y": 469,
              "depth_raw": 4970,
              "depth_meters": 4.970000236062333
            },
            {
              "pixel_x": 219,
              "pixel_y": 469,
              "depth_raw": 5011,
              "depth_meters": 5.0110002380097285
            },
            {
              "pixel_x": 220,
              "pixel_y": 469,
              "depth_raw": 5011,
              "depth_meters": 5.0110002380097285
            },
            {
              "pixel_x": 221,
              "pixel_y": 469,
              "depth_raw": 5011,
              "depth_meters": 5.0110002380097285
            },
            {
              "pixel_x": 212,
              "pixel_y": 470,
              "depth_raw": 4891,
              "depth_meters": 4.891000232310034
            },
            {
              "pixel_x": 213,
              "pixel_y": 470,
              "depth_raw": 4891,
              "depth_meters": 4.891000232310034
            },
            {
              "pixel_x": 214,
              "pixel_y": 470,
              "depth_raw": 4853,
              "depth_meters": 4.853000230505131
            },
            {
              "pixel_x": 215,
              "pixel_y": 470,
              "depth_raw": 4815,
              "depth_meters": 4.815000228700228
            },
            {
              "pixel_x": 216,
              "pixel_y": 470,
              "depth_raw": 4815,
              "depth_meters": 4.815000228700228
            },
            {
              "pixel_x": 217,
              "pixel_y": 470,
              "depth_raw": 4815,
              "depth_meters": 4.815000228700228
            },
            {
              "pixel_x": 218,
              "pixel_y": 470,
              "depth_raw": 4853,
              "depth_meters": 4.853000230505131
            },
            {
              "pixel_x": 219,
              "pixel_y": 470,
              "depth_raw": 4931,
              "depth_meters": 4.931000234209932
            },
            {
              "pixel_x": 220,
              "pixel_y": 470,
              "depth_raw": 4931,
              "depth_meters": 4.931000234209932
            },
            {
              "pixel_x": 221,
              "pixel_y": 470,
              "depth_raw": 4970,
              "depth_meters": 4.970000236062333
            },
            {
              "pixel_x": 212,
              "pixel_y": 471,
              "depth_raw": 4778,
              "depth_meters": 4.778000226942822
            },
            {
              "pixel_x": 213,
              "pixel_y": 471,
              "depth_raw": 4778,
              "depth_meters": 4.778000226942822
            },
            {
              "pixel_x": 214,
              "pixel_y": 471,
              "depth_raw": 4741,
              "depth_meters": 4.741000225185417
            },
            {
              "pixel_x": 215,
              "pixel_y": 471,
              "depth_raw": 4741,
              "depth_meters": 4.741000225185417
            },
            {
              "pixel_x": 216,
              "pixel_y": 471,
              "depth_raw": 4741,
              "depth_meters": 4.741000225185417
            },
            {
              "pixel_x": 217,
              "pixel_y": 471,
              "depth_raw": 4741,
              "depth_meters": 4.741000225185417
            },
            {
              "pixel_x": 218,
              "pixel_y": 471,
              "depth_raw": 4778,
              "depth_meters": 4.778000226942822
            },
            {
              "pixel_x": 219,
              "pixel_y": 471,
              "depth_raw": 4815,
              "depth_meters": 4.815000228700228
            },
            {
              "pixel_x": 220,
              "pixel_y": 471,
              "depth_raw": 4815,
              "depth_meters": 4.815000228700228
            },
            {
              "pixel_x": 221,
              "pixel_y": 471,
              "depth_raw": 4853,
              "depth_meters": 4.853000230505131
            },
            {
              "pixel_x": 212,
              "pixel_y": 472,
              "depth_raw": 4778,
              "depth_meters": 4.778000226942822
            },
            {
              "pixel_x": 213,
              "pixel_y": 472,
              "depth_raw": 4778,
              "depth_meters": 4.778000226942822
            },
            {
              "pixel_x": 214,
              "pixel_y": 472,
              "depth_raw": 4741,
              "depth_meters": 4.741000225185417
            },
            {
              "pixel_x": 215,
              "pixel_y": 472,
              "depth_raw": 4741,
              "depth_meters": 4.741000225185417
            },
            {
              "pixel_x": 216,
              "pixel_y": 472,
              "depth_raw": 4741,
              "depth_meters": 4.741000225185417
            },
            {
              "pixel_x": 217,
              "pixel_y": 472,
              "depth_raw": 4741,
              "depth_meters": 4.741000225185417
            },
            {
              "pixel_x": 218,
              "pixel_y": 472,
              "depth_raw": 4778,
              "depth_meters": 4.778000226942822
            },
            {
              "pixel_x": 219,
              "pixel_y": 472,
              "depth_raw": 4815,
              "depth_meters": 4.815000228700228
            },
            {
              "pixel_x": 220,
              "pixel_y": 472,
              "depth_raw": 4815,
              "depth_meters": 4.815000228700228
            },
            {
              "pixel_x": 221,
              "pixel_y": 472,
              "depth_raw": 4853,
              "depth_meters": 4.853000230505131
            },
            {
              "pixel_x": 212,
              "pixel_y": 473,
              "depth_raw": 4705,
              "depth_meters": 4.705000223475508
            },
            {
              "pixel_x": 213,
              "pixel_y": 473,
              "depth_raw": 4705,
              "depth_meters": 4.705000223475508
            },
            {
              "pixel_x": 214,
              "pixel_y": 473,
              "depth_raw": 4669,
              "depth_meters": 4.6690002217656
            },
            {
              "pixel_x": 215,
              "pixel_y": 473,
              "depth_raw": 4669,
              "depth_meters": 4.6690002217656
            },
            {
              "pixel_x": 216,
              "pixel_y": 473,
              "depth_raw": 4669,
              "depth_meters": 4.6690002217656
            },
            {
              "pixel_x": 217,
              "pixel_y": 473,
              "depth_raw": 4669,
              "depth_meters": 4.6690002217656
            },
            {
              "pixel_x": 218,
              "pixel_y": 473,
              "depth_raw": 4705,
              "depth_meters": 4.705000223475508
            },
            {
              "pixel_x": 219,
              "pixel_y": 473,
              "depth_raw": 4741,
              "depth_meters": 4.741000225185417
            },
            {
              "pixel_x": 220,
              "pixel_y": 473,
              "depth_raw": 4741,
              "depth_meters": 4.741000225185417
            },
            {
              "pixel_x": 221,
              "pixel_y": 473,
              "depth_raw": 4815,
              "depth_meters": 4.815000228700228
            },
            {
              "pixel_x": 212,
              "pixel_y": 474,
              "depth_raw": 4634,
              "depth_meters": 4.634000220103189
            },
            {
              "pixel_x": 213,
              "pixel_y": 474,
              "depth_raw": 4634,
              "depth_meters": 4.634000220103189
            },
            {
              "pixel_x": 214,
              "pixel_y": 474,
              "depth_raw": 4634,
              "depth_meters": 4.634000220103189
            },
            {
              "pixel_x": 215,
              "pixel_y": 474,
              "depth_raw": 4634,
              "depth_meters": 4.634000220103189
            },
            {
              "pixel_x": 216,
              "pixel_y": 474,
              "depth_raw": 4634,
              "depth_meters": 4.634000220103189
            },
            {
              "pixel_x": 217,
              "pixel_y": 474,
              "depth_raw": 4634,
              "depth_meters": 4.634000220103189
            },
            {
              "pixel_x": 218,
              "pixel_y": 474,
              "depth_raw": 4669,
              "depth_meters": 4.6690002217656
            },
            {
              "pixel_x": 219,
              "pixel_y": 474,
              "depth_raw": 4669,
              "depth_meters": 4.6690002217656
            },
            {
              "pixel_x": 220,
              "pixel_y": 474,
              "depth_raw": 4705,
              "depth_meters": 4.705000223475508
            },
            {
              "pixel_x": 221,
              "pixel_y": 474,
              "depth_raw": 4778,
              "depth_meters": 4.778000226942822
            },
            {
              "pixel_x": 212,
              "pixel_y": 475,
              "depth_raw": 4634,
              "depth_meters": 4.634000220103189
            },
            {
              "pixel_x": 213,
              "pixel_y": 475,
              "depth_raw": 4634,
              "depth_meters": 4.634000220103189
            },
            {
              "pixel_x": 214,
              "pixel_y": 475,
              "depth_raw": 4634,
              "depth_meters": 4.634000220103189
            },
            {
              "pixel_x": 215,
              "pixel_y": 475,
              "depth_raw": 4634,
              "depth_meters": 4.634000220103189
            },
            {
              "pixel_x": 216,
              "pixel_y": 475,
              "depth_raw": 4634,
              "depth_meters": 4.634000220103189
            },
            {
              "pixel_x": 217,
              "pixel_y": 475,
              "depth_raw": 4634,
              "depth_meters": 4.634000220103189
            },
            {
              "pixel_x": 218,
              "pixel_y": 475,
              "depth_raw": 4669,
              "depth_meters": 4.6690002217656
            },
            {
              "pixel_x": 219,
              "pixel_y": 475,
              "depth_raw": 4669,
              "depth_meters": 4.6690002217656
            },
            {
              "pixel_x": 220,
              "pixel_y": 475,
              "depth_raw": 4705,
              "depth_meters": 4.705000223475508
            },
            {
              "pixel_x": 221,
              "pixel_y": 475,
              "depth_raw": 4778,
              "depth_meters": 4.778000226942822
            },
            {
              "pixel_x": 212,
              "pixel_y": 476,
              "depth_raw": 4599,
              "depth_meters": 4.5990002184407786
            },
            {
              "pixel_x": 213,
              "pixel_y": 476,
              "depth_raw": 4599,
              "depth_meters": 4.5990002184407786
            },
            {
              "pixel_x": 214,
              "pixel_y": 476,
              "depth_raw": 4565,
              "depth_meters": 4.565000216825865
            },
            {
              "pixel_x": 215,
              "pixel_y": 476,
              "depth_raw": 4565,
              "depth_meters": 4.565000216825865
            },
            {
              "pixel_x": 216,
              "pixel_y": 476,
              "depth_raw": 4599,
              "depth_meters": 4.5990002184407786
            },
            {
              "pixel_x": 217,
              "pixel_y": 476,
              "depth_raw": 4599,
              "depth_meters": 4.5990002184407786
            },
            {
              "pixel_x": 218,
              "pixel_y": 476,
              "depth_raw": 4634,
              "depth_meters": 4.634000220103189
            },
            {
              "pixel_x": 219,
              "pixel_y": 476,
              "depth_raw": 4634,
              "depth_meters": 4.634000220103189
            },
            {
              "pixel_x": 220,
              "pixel_y": 476,
              "depth_raw": 4669,
              "depth_meters": 4.6690002217656
            },
            {
              "pixel_x": 221,
              "pixel_y": 476,
              "depth_raw": 4705,
              "depth_meters": 4.705000223475508
            },
            {
              "pixel_x": 212,
              "pixel_y": 477,
              "depth_raw": 4599,
              "depth_meters": 4.5990002184407786
            },
            {
              "pixel_x": 213,
              "pixel_y": 477,
              "depth_raw": 4599,
              "depth_meters": 4.5990002184407786
            },
            {
              "pixel_x": 214,
              "pixel_y": 477,
              "depth_raw": 4565,
              "depth_meters": 4.565000216825865
            },
            {
              "pixel_x": 215,
              "pixel_y": 477,
              "depth_raw": 4565,
              "depth_meters": 4.565000216825865
            },
            {
              "pixel_x": 216,
              "pixel_y": 477,
              "depth_raw": 4565,
              "depth_meters": 4.565000216825865
            },
            {
              "pixel_x": 217,
              "pixel_y": 477,
              "depth_raw": 4565,
              "depth_meters": 4.565000216825865
            },
            {
              "pixel_x": 218,
              "pixel_y": 477,
              "depth_raw": 4634,
              "depth_meters": 4.634000220103189
            },
            {
              "pixel_x": 219,
              "pixel_y": 477,
              "depth_raw": 4634,
              "depth_meters": 4.634000220103189
            },
            {
              "pixel_x": 220,
              "pixel_y": 477,
              "depth_raw": 4669,
              "depth_meters": 4.6690002217656
            },
            {
              "pixel_x": 221,
              "pixel_y": 477,
              "depth_raw": 4705,
              "depth_meters": 4.705000223475508
            }
          ],
          "depth_scale_used": 0.0010000000474974513,
          "bounding_box_depth": {
            "roi_shape": [
              14,
              10
            ],
            "mean_raw": 4889.835714285714,
            "median_raw": 4815.0
          }
        }
      }
    },
    {
      "detection_id": 2,
      "class_id": 1,
      "confidence": 0.8153847455978394,
      "bounding_box": {
        "x1": 257,
        "y1": 462,
        "x2": 267,
        "y2": 475,
        "center_x": 262,
        "center_y": 468,
        "width": 10,
        "height": 13
      },
      "relative_coordinates": {
        "rel_x": -58.0,
        "rel_y": 228.0
      },
      "depth_information": {
        "statistics": {
          "mean_depth": 5.2469694799868964,
          "median_depth": 5.223000248079188,
          "min_depth": 4.853000230505131,
          "max_depth": 6.289000298711471,
          "std_depth": 0.3401689320812114,
          "valid_pixels": 130,
          "total_pixels": 130,
          "fill_ratio": 1.0
        },
        "realsense_depth_data": {
          "center_point": {
            "pixel_x": 262,
            "pixel_y": 468,
            "depth_raw": 5179,
            "depth_meters": 5.1790002459893
          },
          "sample_points": [
            {
              "pixel_x": 257,
              "pixel_y": 462,
              "depth_raw": 5313,
              "depth_meters": 5.313000252353959
            },
            {
              "pixel_x": 258,
              "pixel_y": 462,
              "depth_raw": 5359,
              "depth_meters": 5.3590002545388415
            },
            {
              "pixel_x": 259,
              "pixel_y": 462,
              "depth_raw": 5359,
              "depth_meters": 5.3590002545388415
            },
            {
              "pixel_x": 260,
              "pixel_y": 462,
              "depth_raw": 5406,
              "depth_meters": 5.406000256771222
            },
            {
              "pixel_x": 261,
              "pixel_y": 462,
              "depth_raw": 5406,
              "depth_meters": 5.406000256771222
            },
            {
              "pixel_x": 262,
              "pixel_y": 462,
              "depth_raw": 5654,
              "depth_meters": 5.65400026855059
            },
            {
              "pixel_x": 263,
              "pixel_y": 462,
              "depth_raw": 5926,
              "depth_meters": 5.926000281469896
            },
            {
              "pixel_x": 264,
              "pixel_y": 462,
              "depth_raw": 5926,
              "depth_meters": 5.926000281469896
            },
            {
              "pixel_x": 265,
              "pixel_y": 462,
              "depth_raw": 6102,
              "depth_meters": 6.102000289829448
            },
            {
              "pixel_x": 266,
              "pixel_y": 462,
              "depth_raw": 6289,
              "depth_meters": 6.289000298711471
            },
            {
              "pixel_x": 257,
              "pixel_y": 463,
              "depth_raw": 5313,
              "depth_meters": 5.313000252353959
            },
            {
              "pixel_x": 258,
              "pixel_y": 463,
              "depth_raw": 5359,
              "depth_meters": 5.3590002545388415
            },
            {
              "pixel_x": 259,
              "pixel_y": 463,
              "depth_raw": 5359,
              "depth_meters": 5.3590002545388415
            },
            {
              "pixel_x": 260,
              "pixel_y": 463,
              "depth_raw": 5406,
              "depth_meters": 5.406000256771222
            },
            {
              "pixel_x": 261,
              "pixel_y": 463,
              "depth_raw": 5406,
              "depth_meters": 5.406000256771222
            },
            {
              "pixel_x": 262,
              "pixel_y": 463,
              "depth_raw": 5654,
              "depth_meters": 5.65400026855059
            },
            {
              "pixel_x": 263,
              "pixel_y": 463,
              "depth_raw": 5926,
              "depth_meters": 5.926000281469896
            },
            {
              "pixel_x": 264,
              "pixel_y": 463,
              "depth_raw": 5926,
              "depth_meters": 5.926000281469896
            },
            {
              "pixel_x": 265,
              "pixel_y": 463,
              "depth_raw": 6102,
              "depth_meters": 6.102000289829448
            },
            {
              "pixel_x": 266,
              "pixel_y": 463,
              "depth_raw": 6289,
              "depth_meters": 6.289000298711471
            },
            {
              "pixel_x": 257,
              "pixel_y": 464,
              "depth_raw": 5223,
              "depth_meters": 5.223000248079188
            },
            {
              "pixel_x": 258,
              "pixel_y": 464,
              "depth_raw": 5223,
              "depth_meters": 5.223000248079188
            },
            {
              "pixel_x": 259,
              "pixel_y": 464,
              "depth_raw": 5223,
              "depth_meters": 5.223000248079188
            },
            {
              "pixel_x": 260,
              "pixel_y": 464,
              "depth_raw": 5313,
              "depth_meters": 5.313000252353959
            },
            {
              "pixel_x": 261,
              "pixel_y": 464,
              "depth_raw": 5313,
              "depth_meters": 5.313000252353959
            },
            {
              "pixel_x": 262,
              "pixel_y": 464,
              "depth_raw": 5454,
              "depth_meters": 5.454000259051099
            },
            {
              "pixel_x": 263,
              "pixel_y": 464,
              "depth_raw": 5707,
              "depth_meters": 5.707000271067955
            },
            {
              "pixel_x": 264,
              "pixel_y": 464,
              "depth_raw": 5707,
              "depth_meters": 5.707000271067955
            },
            {
              "pixel_x": 265,
              "pixel_y": 464,
              "depth_raw": 5870,
              "depth_meters": 5.870000278810039
            },
            {
              "pixel_x": 266,
              "pixel_y": 464,
              "depth_raw": 6042,
              "depth_meters": 6.042000286979601
            },
            {
              "pixel_x": 257,
              "pixel_y": 465,
              "depth_raw": 5223,
              "depth_meters": 5.223000248079188
            },
            {
              "pixel_x": 258,
              "pixel_y": 465,
              "depth_raw": 5223,
              "depth_meters": 5.223000248079188
            },
            {
              "pixel_x": 259,
              "pixel_y": 465,
              "depth_raw": 5223,
              "depth_meters": 5.223000248079188
            },
            {
              "pixel_x": 260,
              "pixel_y": 465,
              "depth_raw": 5313,
              "depth_meters": 5.313000252353959
            },
            {
              "pixel_x": 261,
              "pixel_y": 465,
              "depth_raw": 5313,
              "depth_meters": 5.313000252353959
            },
            {
              "pixel_x": 262,
              "pixel_y": 465,
              "depth_raw": 5454,
              "depth_meters": 5.454000259051099
            },
            {
              "pixel_x": 263,
              "pixel_y": 465,
              "depth_raw": 5707,
              "depth_meters": 5.707000271067955
            },
            {
              "pixel_x": 264,
              "pixel_y": 465,
              "depth_raw": 5654,
              "depth_meters": 5.65400026855059
            },
            {
              "pixel_x": 265,
              "pixel_y": 465,
              "depth_raw": 5654,
              "depth_meters": 5.65400026855059
            },
            {
              "pixel_x": 266,
              "pixel_y": 465,
              "depth_raw": 5814,
              "depth_meters": 5.814000276150182
            },
            {
              "pixel_x": 257,
              "pixel_y": 466,
              "depth_raw": 5094,
              "depth_meters": 5.094000241952017
            },
            {
              "pixel_x": 258,
              "pixel_y": 466,
              "depth_raw": 5094,
              "depth_meters": 5.094000241952017
            },
            {
              "pixel_x": 259,
              "pixel_y": 466,
              "depth_raw": 5136,
              "depth_meters": 5.13600024394691
            },
            {
              "pixel_x": 260,
              "pixel_y": 466,
              "depth_raw": 5136,
              "depth_meters": 5.13600024394691
            },
            {
              "pixel_x": 261,
              "pixel_y": 466,
              "depth_raw": 5136,
              "depth_meters": 5.13600024394691
            },
            {
              "pixel_x": 262,
              "pixel_y": 466,
              "depth_raw": 5313,
              "depth_meters": 5.313000252353959
            },
            {
              "pixel_x": 263,
              "pixel_y": 466,
              "depth_raw": 5552,
              "depth_meters": 5.55200026370585
            },
            {
              "pixel_x": 264,
              "pixel_y": 466,
              "depth_raw": 5552,
              "depth_meters": 5.55200026370585
            },
            {
              "pixel_x": 265,
              "pixel_y": 466,
              "depth_raw": 5654,
              "depth_meters": 5.65400026855059
            },
            {
              "pixel_x": 266,
              "pixel_y": 466,
              "depth_raw": 5814,
              "depth_meters": 5.814000276150182
            },
            {
              "pixel_x": 257,
              "pixel_y": 467,
              "depth_raw": 5011,
              "depth_meters": 5.0110002380097285
            },
            {
              "pixel_x": 258,
              "pixel_y": 467,
              "depth_raw": 5011,
              "depth_meters": 5.0110002380097285
            },
            {
              "pixel_x": 259,
              "pixel_y": 467,
              "depth_raw": 5011,
              "depth_meters": 5.0110002380097285
            },
            {
              "pixel_x": 260,
              "pixel_y": 467,
              "depth_raw": 5052,
              "depth_meters": 5.052000239957124
            },
            {
              "pixel_x": 261,
              "pixel_y": 467,
              "depth_raw": 5052,
              "depth_meters": 5.052000239957124
            },
            {
              "pixel_x": 262,
              "pixel_y": 467,
              "depth_raw": 5179,
              "depth_meters": 5.1790002459893
            },
            {
              "pixel_x": 263,
              "pixel_y": 467,
              "depth_raw": 5359,
              "depth_meters": 5.3590002545388415
            },
            {
              "pixel_x": 264,
              "pixel_y": 467,
              "depth_raw": 5359,
              "depth_meters": 5.3590002545388415
            },
            {
              "pixel_x": 265,
              "pixel_y": 467,
              "depth_raw": 5503,
              "depth_meters": 5.5030002613784745
            },
            {
              "pixel_x": 266,
              "pixel_y": 467,
              "depth_raw": 5552,
              "depth_meters": 5.55200026370585
            },
            {
              "pixel_x": 257,
              "pixel_y": 468,
              "depth_raw": 5011,
              "depth_meters": 5.0110002380097285
            },
            {
              "pixel_x": 258,
              "pixel_y": 468,
              "depth_raw": 5011,
              "depth_meters": 5.0110002380097285
            },
            {
              "pixel_x": 259,
              "pixel_y": 468,
              "depth_raw": 5011,
              "depth_meters": 5.0110002380097285
            },
            {
              "pixel_x": 260,
              "pixel_y": 468,
              "depth_raw": 5052,
              "depth_meters": 5.052000239957124
            },
            {
              "pixel_x": 261,
              "pixel_y": 468,
              "depth_raw": 5052,
              "depth_meters": 5.052000239957124
            },
            {
              "pixel_x": 262,
              "pixel_y": 468,
              "depth_raw": 5179,
              "depth_meters": 5.1790002459893
            },
            {
              "pixel_x": 263,
              "pixel_y": 468,
              "depth_raw": 5359,
              "depth_meters": 5.3590002545388415
            },
            {
              "pixel_x": 264,
              "pixel_y": 468,
              "depth_raw": 5359,
              "depth_meters": 5.3590002545388415
            },
            {
              "pixel_x": 265,
              "pixel_y": 468,
              "depth_raw": 5503,
              "depth_meters": 5.5030002613784745
            },
            {
              "pixel_x": 266,
              "pixel_y": 468,
              "depth_raw": 5552,
              "depth_meters": 5.55200026370585
            },
            {
              "pixel_x": 257,
              "pixel_y": 469,
              "depth_raw": 4931,
              "depth_meters": 4.931000234209932
            },
            {
              "pixel_x": 258,
              "pixel_y": 469,
              "depth_raw": 4931,
              "depth_meters": 4.931000234209932
            },
            {
              "pixel_x": 259,
              "pixel_y": 469,
              "depth_raw": 4970,
              "depth_meters": 4.970000236062333
            },
            {
              "pixel_x": 260,
              "pixel_y": 469,
              "depth_raw": 4970,
              "depth_meters": 4.970000236062333
            },
            {
              "pixel_x": 261,
              "pixel_y": 469,
              "depth_raw": 4970,
              "depth_meters": 4.970000236062333
            },
            {
              "pixel_x": 262,
              "pixel_y": 469,
              "depth_raw": 5052,
              "depth_meters": 5.052000239957124
            },
            {
              "pixel_x": 263,
              "pixel_y": 469,
              "depth_raw": 5223,
              "depth_meters": 5.223000248079188
            },
            {
              "pixel_x": 264,
              "pixel_y": 469,
              "depth_raw": 5223,
              "depth_meters": 5.223000248079188
            },
            {
              "pixel_x": 265,
              "pixel_y": 469,
              "depth_raw": 5359,
              "depth_meters": 5.3590002545388415
            },
            {
              "pixel_x": 266,
              "pixel_y": 469,
              "depth_raw": 5454,
              "depth_meters": 5.454000259051099
            },
            {
              "pixel_x": 257,
              "pixel_y": 470,
              "depth_raw": 4891,
              "depth_meters": 4.891000232310034
            },
            {
              "pixel_x": 258,
              "pixel_y": 470,
              "depth_raw": 4891,
              "depth_meters": 4.891000232310034
            },
            {
              "pixel_x": 259,
              "pixel_y": 470,
              "depth_raw": 4891,
              "depth_meters": 4.891000232310034
            },
            {
              "pixel_x": 260,
              "pixel_y": 470,
              "depth_raw": 4931,
              "depth_meters": 4.931000234209932
            },
            {
              "pixel_x": 261,
              "pixel_y": 470,
              "depth_raw": 4931,
              "depth_meters": 4.931000234209932
            },
            {
              "pixel_x": 262,
              "pixel_y": 470,
              "depth_raw": 4970,
              "depth_meters": 4.970000236062333
            },
            {
              "pixel_x": 263,
              "pixel_y": 470,
              "depth_raw": 5094,
              "depth_meters": 5.094000241952017
            },
            {
              "pixel_x": 264,
              "pixel_y": 470,
              "depth_raw": 5094,
              "depth_meters": 5.094000241952017
            },
            {
              "pixel_x": 265,
              "pixel_y": 470,
              "depth_raw": 5223,
              "depth_meters": 5.223000248079188
            },
            {
              "pixel_x": 266,
              "pixel_y": 470,
              "depth_raw": 5454,
              "depth_meters": 5.454000259051099
            },
            {
              "pixel_x": 257,
              "pixel_y": 471,
              "depth_raw": 4891,
              "depth_meters": 4.891000232310034
            },
            {
              "pixel_x": 258,
              "pixel_y": 471,
              "depth_raw": 4891,
              "depth_meters": 4.891000232310034
            },
            {
              "pixel_x": 259,
              "pixel_y": 471,
              "depth_raw": 4891,
              "depth_meters": 4.891000232310034
            },
            {
              "pixel_x": 260,
              "pixel_y": 471,
              "depth_raw": 4931,
              "depth_meters": 4.931000234209932
            },
            {
              "pixel_x": 261,
              "pixel_y": 471,
              "depth_raw": 4931,
              "depth_meters": 4.931000234209932
            },
            {
              "pixel_x": 262,
              "pixel_y": 471,
              "depth_raw": 4970,
              "depth_meters": 4.970000236062333
            },
            {
              "pixel_x": 263,
              "pixel_y": 471,
              "depth_raw": 5094,
              "depth_meters": 5.094000241952017
            },
            {
              "pixel_x": 264,
              "pixel_y": 471,
              "depth_raw": 5094,
              "depth_meters": 5.094000241952017
            },
            {
              "pixel_x": 265,
              "pixel_y": 471,
              "depth_raw": 5223,
              "depth_meters": 5.223000248079188
            },
            {
              "pixel_x": 266,
              "pixel_y": 471,
              "depth_raw": 5454,
              "depth_meters": 5.454000259051099
            },
            {
              "pixel_x": 257,
              "pixel_y": 472,
              "depth_raw": 4853,
              "depth_meters": 4.853000230505131
            },
            {
              "pixel_x": 258,
              "pixel_y": 472,
              "depth_raw": 4853,
              "depth_meters": 4.853000230505131
            },
            {
              "pixel_x": 259,
              "pixel_y": 472,
              "depth_raw": 4853,
              "depth_meters": 4.853000230505131
            },
            {
              "pixel_x": 260,
              "pixel_y": 472,
              "depth_raw": 4891,
              "depth_meters": 4.891000232310034
            },
            {
              "pixel_x": 261,
              "pixel_y": 472,
              "depth_raw": 4891,
              "depth_meters": 4.891000232310034
            },
            {
              "pixel_x": 262,
              "pixel_y": 472,
              "depth_raw": 4931,
              "depth_meters": 4.931000234209932
            },
            {
              "pixel_x": 263,
              "pixel_y": 472,
              "depth_raw": 5094,
              "depth_meters": 5.094000241952017
            },
            {
              "pixel_x": 264,
              "pixel_y": 472,
              "depth_raw": 5094,
              "depth_meters": 5.094000241952017
            },
            {
              "pixel_x": 265,
              "pixel_y": 472,
              "depth_raw": 5223,
              "depth_meters": 5.223000248079188
            },
            {
              "pixel_x": 266,
              "pixel_y": 472,
              "depth_raw": 5454,
              "depth_meters": 5.454000259051099
            },
            {
              "pixel_x": 257,
              "pixel_y": 473,
              "depth_raw": 4853,
              "depth_meters": 4.853000230505131
            },
            {
              "pixel_x": 258,
              "pixel_y": 473,
              "depth_raw": 4853,
              "depth_meters": 4.853000230505131
            },
            {
              "pixel_x": 259,
              "pixel_y": 473,
              "depth_raw": 4853,
              "depth_meters": 4.853000230505131
            },
            {
              "pixel_x": 260,
              "pixel_y": 473,
              "depth_raw": 4853,
              "depth_meters": 4.853000230505131
            },
            {
              "pixel_x": 261,
              "pixel_y": 473,
              "depth_raw": 4853,
              "depth_meters": 4.853000230505131
            },
            {
              "pixel_x": 262,
              "pixel_y": 473,
              "depth_raw": 4891,
              "depth_meters": 4.891000232310034
            },
            {
              "pixel_x": 263,
              "pixel_y": 473,
              "depth_raw": 4891,
              "depth_meters": 4.891000232310034
            },
            {
              "pixel_x": 264,
              "pixel_y": 473,
              "depth_raw": 5094,
              "depth_meters": 5.094000241952017
            },
            {
              "pixel_x": 265,
              "pixel_y": 473,
              "depth_raw": 5268,
              "depth_meters": 5.2680002502165735
            },
            {
              "pixel_x": 266,
              "pixel_y": 473,
              "depth_raw": 5268,
              "depth_meters": 5.2680002502165735
            },
            {
              "pixel_x": 257,
              "pixel_y": 474,
              "depth_raw": 4853,
              "depth_meters": 4.853000230505131
            },
            {
              "pixel_x": 258,
              "pixel_y": 474,
              "depth_raw": 4853,
              "depth_meters": 4.853000230505131
            },
            {
              "pixel_x": 259,
              "pixel_y": 474,
              "depth_raw": 4853,
              "depth_meters": 4.853000230505131
            },
            {
              "pixel_x": 260,
              "pixel_y": 474,
              "depth_raw": 4853,
              "depth_meters": 4.853000230505131
            },
            {
              "pixel_x": 261,
              "pixel_y": 474,
              "depth_raw": 4853,
              "depth_meters": 4.853000230505131
            },
            {
              "pixel_x": 262,
              "pixel_y": 474,
              "depth_raw": 4891,
              "depth_meters": 4.891000232310034
            },
            {
              "pixel_x": 263,
              "pixel_y": 474,
              "depth_raw": 4891,
              "depth_meters": 4.891000232310034
            },
            {
              "pixel_x": 264,
              "pixel_y": 474,
              "depth_raw": 5094,
              "depth_meters": 5.094000241952017
            },
            {
              "pixel_x": 265,
              "pixel_y": 474,
              "depth_raw": 5268,
              "depth_meters": 5.2680002502165735
            },
            {
              "pixel_x": 266,
              "pixel_y": 474,
              "depth_raw": 5268,
              "depth_meters": 5.2680002502165735
            }
          ],
          "depth_scale_used": 0.0010000000474974513,
          "bounding_box_depth": {
            "roi_shape": [
              13,
              10
            ],
            "mean_raw": 5246.969230769231,
            "median_raw": 5223.0
          }
        }
      }
    },
    {
      "detection_id": 3,
      "class_id": 0,
      "confidence": 0.7604092359542847,
      "bounding_box": {
        "x1": 307,
        "y1": 462,
        "x2": 317,
        "y2": 476,
        "center_x": 312,
        "center_y": 469,
        "width": 10,
        "height": 14
      },
      "relative_coordinates": {
        "rel_x": -8.0,
        "rel_y": 229.0
      },
      "depth_information": {
        "statistics": {
          "mean_depth": 5.565108959980654,
          "median_depth": 5.406000256771222,
          "min_depth": 4.565000216825865,
          "max_depth": 7.3370003484888,
          "std_depth": 0.7895338724889677,
          "valid_pixels": 138,
          "total_pixels": 140,
          "fill_ratio": 0.9857142857142858
        },
        "realsense_depth_data": {
          "center_point": {
            "pixel_x": 312,
            "pixel_y": 469,
            "depth_raw": 5136,
            "depth_meters": 5.13600024394691
          },
          "sample_points": [
            {
              "pixel_x": 307,
              "pixel_y": 462,
              "depth_raw": 7337,
              "depth_meters": 7.3370003484888
            },
            {
              "pixel_x": 308,
              "pixel_y": 462,
              "depth_raw": 7337,
              "depth_meters": 7.3370003484888
            },
            {
              "pixel_x": 309,
              "pixel_y": 462,
              "depth_raw": 7337,
              "depth_meters": 7.3370003484888
            },
            {
              "pixel_x": 310,
              "pixel_y": 462,
              "depth_raw": 7251,
              "depth_meters": 7.251000344404019
            },
            {
              "pixel_x": 311,
              "pixel_y": 462,
              "depth_raw": 7251,
              "depth_meters": 7.251000344404019
            },
            {
              "pixel_x": 312,
              "pixel_y": 462,
              "depth_raw": 7166,
              "depth_meters": 7.166000340366736
            },
            {
              "pixel_x": 313,
              "pixel_y": 462,
              "depth_raw": 7166,
              "depth_meters": 7.166000340366736
            },
            {
              "pixel_x": 314,
              "pixel_y": 462,
              "depth_raw": 7084,
              "depth_meters": 7.084000336471945
            },
            {
              "pixel_x": 315,
              "pixel_y": 462,
              "depth_raw": 7004,
              "depth_meters": 7.004000332672149
            },
            {
              "pixel_x": 316,
              "pixel_y": 462,
              "depth_raw": 7004,
              "depth_meters": 7.004000332672149
            },
            {
              "pixel_x": 307,
              "pixel_y": 463,
              "depth_raw": 6773,
              "depth_meters": 6.773000321700238
            },
            {
              "pixel_x": 308,
              "pixel_y": 463,
              "depth_raw": 6773,
              "depth_meters": 6.773000321700238
            },
            {
              "pixel_x": 309,
              "pixel_y": 463,
              "depth_raw": 6699,
              "depth_meters": 6.699000318185426
            },
            {
              "pixel_x": 310,
              "pixel_y": 463,
              "depth_raw": 6699,
              "depth_meters": 6.699000318185426
            },
            {
              "pixel_x": 311,
              "pixel_y": 463,
              "depth_raw": 6627,
              "depth_meters": 6.62700031476561
            },
            {
              "pixel_x": 312,
              "pixel_y": 463,
              "depth_raw": 6627,
              "depth_meters": 6.62700031476561
            },
            {
              "pixel_x": 313,
              "pixel_y": 463,
              "depth_raw": 6627,
              "depth_meters": 6.62700031476561
            },
            {
              "pixel_x": 314,
              "pixel_y": 463,
              "depth_raw": 6557,
              "depth_meters": 6.557000311440788
            },
            {
              "pixel_x": 315,
              "pixel_y": 463,
              "depth_raw": 6557,
              "depth_meters": 6.557000311440788
            },
            {
              "pixel_x": 316,
              "pixel_y": 463,
              "depth_raw": 6627,
              "depth_meters": 6.62700031476561
            },
            {
              "pixel_x": 307,
              "pixel_y": 464,
              "depth_raw": 6773,
              "depth_meters": 6.773000321700238
            },
            {
              "pixel_x": 308,
              "pixel_y": 464,
              "depth_raw": 6773,
              "depth_meters": 6.773000321700238
            },
            {
              "pixel_x": 309,
              "pixel_y": 464,
              "depth_raw": 6699,
              "depth_meters": 6.699000318185426
            },
            {
              "pixel_x": 310,
              "pixel_y": 464,
              "depth_raw": 6699,
              "depth_meters": 6.699000318185426
            },
            {
              "pixel_x": 311,
              "pixel_y": 464,
              "depth_raw": 6627,
              "depth_meters": 6.62700031476561
            },
            {
              "pixel_x": 312,
              "pixel_y": 464,
              "depth_raw": 6163,
              "depth_meters": 6.163000292726792
            },
            {
              "pixel_x": 313,
              "pixel_y": 464,
              "depth_raw": 6163,
              "depth_meters": 6.163000292726792
            },
            {
              "pixel_x": 314,
              "pixel_y": 464,
              "depth_raw": 6163,
              "depth_meters": 6.163000292726792
            },
            {
              "pixel_x": 315,
              "pixel_y": 464,
              "depth_raw": 6163,
              "depth_meters": 6.163000292726792
            },
            {
              "pixel_x": 316,
              "pixel_y": 464,
              "depth_raw": 6163,
              "depth_meters": 6.163000292726792
            },
            {
              "pixel_x": 307,
              "pixel_y": 465,
              "depth_raw": 6289,
              "depth_meters": 6.289000298711471
            },
            {
              "pixel_x": 308,
              "pixel_y": 465,
              "depth_raw": 6225,
              "depth_meters": 6.225000295671634
            },
            {
              "pixel_x": 309,
              "pixel_y": 465,
              "depth_raw": 6225,
              "depth_meters": 6.225000295671634
            },
            {
              "pixel_x": 310,
              "pixel_y": 465,
              "depth_raw": 6225,
              "depth_meters": 6.225000295671634
            },
            {
              "pixel_x": 311,
              "pixel_y": 465,
              "depth_raw": 6163,
              "depth_meters": 6.163000292726792
            },
            {
              "pixel_x": 312,
              "pixel_y": 465,
              "depth_raw": 6163,
              "depth_meters": 6.163000292726792
            },
            {
              "pixel_x": 313,
              "pixel_y": 465,
              "depth_raw": 6163,
              "depth_meters": 6.163000292726792
            },
            {
              "pixel_x": 314,
              "pixel_y": 465,
              "depth_raw": 6163,
              "depth_meters": 6.163000292726792
            },
            {
              "pixel_x": 315,
              "pixel_y": 465,
              "depth_raw": 6163,
              "depth_meters": 6.163000292726792
            },
            {
              "pixel_x": 316,
              "pixel_y": 465,
              "depth_raw": 6163,
              "depth_meters": 6.163000292726792
            },
            {
              "pixel_x": 307,
              "pixel_y": 466,
              "depth_raw": 5814,
              "depth_meters": 5.814000276150182
            },
            {
              "pixel_x": 308,
              "pixel_y": 466,
              "depth_raw": 5814,
              "depth_meters": 5.814000276150182
            },
            {
              "pixel_x": 309,
              "pixel_y": 466,
              "depth_raw": 5814,
              "depth_meters": 5.814000276150182
            },
            {
              "pixel_x": 310,
              "pixel_y": 466,
              "depth_raw": 5814,
              "depth_meters": 5.814000276150182
            },
            {
              "pixel_x": 311,
              "pixel_y": 466,
              "depth_raw": 5814,
              "depth_meters": 5.814000276150182
            },
            {
              "pixel_x": 312,
              "pixel_y": 466,
              "depth_raw": 5814,
              "depth_meters": 5.814000276150182
            },
            {
              "pixel_x": 313,
              "pixel_y": 466,
              "depth_raw": 5814,
              "depth_meters": 5.814000276150182
            },
            {
              "pixel_x": 314,
              "pixel_y": 466,
              "depth_raw": 5814,
              "depth_meters": 5.814000276150182
            },
            {
              "pixel_x": 315,
              "pixel_y": 466,
              "depth_raw": 5814,
              "depth_meters": 5.814000276150182
            },
            {
              "pixel_x": 316,
              "pixel_y": 466,
              "depth_raw": 5814,
              "depth_meters": 5.814000276150182
            },
            {
              "pixel_x": 307,
              "pixel_y": 467,
              "depth_raw": 5814,
              "depth_meters": 5.814000276150182
            },
            {
              "pixel_x": 308,
              "pixel_y": 467,
              "depth_raw": 5814,
              "depth_meters": 5.814000276150182
            },
            {
              "pixel_x": 309,
              "pixel_y": 467,
              "depth_raw": 5814,
              "depth_meters": 5.814000276150182
            },
            {
              "pixel_x": 310,
              "pixel_y": 467,
              "depth_raw": 5814,
              "depth_meters": 5.814000276150182
            },
            {
              "pixel_x": 311,
              "pixel_y": 467,
              "depth_raw": 5814,
              "depth_meters": 5.814000276150182
            },
            {
              "pixel_x": 312,
              "pixel_y": 467,
              "depth_raw": 5814,
              "depth_meters": 5.814000276150182
            },
            {
              "pixel_x": 313,
              "pixel_y": 467,
              "depth_raw": 5814,
              "depth_meters": 5.814000276150182
            },
            {
              "pixel_x": 314,
              "pixel_y": 467,
              "depth_raw": 5814,
              "depth_meters": 5.814000276150182
            },
            {
              "pixel_x": 315,
              "pixel_y": 467,
              "depth_raw": 5814,
              "depth_meters": 5.814000276150182
            },
            {
              "pixel_x": 316,
              "pixel_y": 467,
              "depth_raw": 5814,
              "depth_meters": 5.814000276150182
            },
            {
              "pixel_x": 307,
              "pixel_y": 468,
              "depth_raw": 5406,
              "depth_meters": 5.406000256771222
            },
            {
              "pixel_x": 308,
              "pixel_y": 468,
              "depth_raw": 5406,
              "depth_meters": 5.406000256771222
            },
            {
              "pixel_x": 309,
              "pixel_y": 468,
              "depth_raw": 5406,
              "depth_meters": 5.406000256771222
            },
            {
              "pixel_x": 310,
              "pixel_y": 468,
              "depth_raw": 5406,
              "depth_meters": 5.406000256771222
            },
            {
              "pixel_x": 311,
              "pixel_y": 468,
              "depth_raw": 5406,
              "depth_meters": 5.406000256771222
            },
            {
              "pixel_x": 312,
              "pixel_y": 468,
              "depth_raw": 5454,
              "depth_meters": 5.454000259051099
            },
            {
              "pixel_x": 313,
              "pixel_y": 468,
              "depth_raw": 5454,
              "depth_meters": 5.454000259051099
            },
            {
              "pixel_x": 314,
              "pixel_y": 468,
              "depth_raw": 5503,
              "depth_meters": 5.5030002613784745
            },
            {
              "pixel_x": 315,
              "pixel_y": 468,
              "depth_raw": 5503,
              "depth_meters": 5.5030002613784745
            },
            {
              "pixel_x": 316,
              "pixel_y": 468,
              "depth_raw": 5503,
              "depth_meters": 5.5030002613784745
            },
            {
              "pixel_x": 307,
              "pixel_y": 469,
              "depth_raw": 5011,
              "depth_meters": 5.0110002380097285
            },
            {
              "pixel_x": 308,
              "pixel_y": 469,
              "depth_raw": 5011,
              "depth_meters": 5.0110002380097285
            },
            {
              "pixel_x": 309,
              "pixel_y": 469,
              "depth_raw": 5052,
              "depth_meters": 5.052000239957124
            },
            {
              "pixel_x": 310,
              "pixel_y": 469,
              "depth_raw": 5052,
              "depth_meters": 5.052000239957124
            },
            {
              "pixel_x": 311,
              "pixel_y": 469,
              "depth_raw": 5094,
              "depth_meters": 5.094000241952017
            },
            {
              "pixel_x": 312,
              "pixel_y": 469,
              "depth_raw": 5136,
              "depth_meters": 5.13600024394691
            },
            {
              "pixel_x": 313,
              "pixel_y": 469,
              "depth_raw": 5136,
              "depth_meters": 5.13600024394691
            },
            {
              "pixel_x": 314,
              "pixel_y": 469,
              "depth_raw": 5179,
              "depth_meters": 5.1790002459893
            },
            {
              "pixel_x": 315,
              "pixel_y": 469,
              "depth_raw": 5268,
              "depth_meters": 5.2680002502165735
            },
            {
              "pixel_x": 316,
              "pixel_y": 469,
              "depth_raw": 5268,
              "depth_meters": 5.2680002502165735
            },
            {
              "pixel_x": 307,
              "pixel_y": 470,
              "depth_raw": 5011,
              "depth_meters": 5.0110002380097285
            },
            {
              "pixel_x": 308,
              "pixel_y": 470,
              "depth_raw": 5011,
              "depth_meters": 5.0110002380097285
            },
            {
              "pixel_x": 309,
              "pixel_y": 470,
              "depth_raw": 5052,
              "depth_meters": 5.052000239957124
            },
            {
              "pixel_x": 310,
              "pixel_y": 470,
              "depth_raw": 5052,
              "depth_meters": 5.052000239957124
            },
            {
              "pixel_x": 311,
              "pixel_y": 470,
              "depth_raw": 5094,
              "depth_meters": 5.094000241952017
            },
            {
              "pixel_x": 312,
              "pixel_y": 470,
              "depth_raw": 5136,
              "depth_meters": 5.13600024394691
            },
            {
              "pixel_x": 313,
              "pixel_y": 470,
              "depth_raw": 5136,
              "depth_meters": 5.13600024394691
            },
            {
              "pixel_x": 314,
              "pixel_y": 470,
              "depth_raw": 5179,
              "depth_meters": 5.1790002459893
            },
            {
              "pixel_x": 315,
              "pixel_y": 470,
              "depth_raw": 5268,
              "depth_meters": 5.2680002502165735
            },
            {
              "pixel_x": 316,
              "pixel_y": 470,
              "depth_raw": 5268,
              "depth_meters": 5.2680002502165735
            },
            {
              "pixel_x": 307,
              "pixel_y": 471,
              "depth_raw": 4741,
              "depth_meters": 4.741000225185417
            },
            {
              "pixel_x": 308,
              "pixel_y": 471,
              "depth_raw": 5011,
              "depth_meters": 5.0110002380097285
            },
            {
              "pixel_x": 309,
              "pixel_y": 471,
              "depth_raw": 5052,
              "depth_meters": 5.052000239957124
            },
            {
              "pixel_x": 310,
              "pixel_y": 471,
              "depth_raw": 4815,
              "depth_meters": 4.815000228700228
            },
            {
              "pixel_x": 311,
              "pixel_y": 471,
              "depth_raw": 4815,
              "depth_meters": 4.815000228700228
            },
            {
              "pixel_x": 312,
              "pixel_y": 471,
              "depth_raw": 4891,
              "depth_meters": 4.891000232310034
            },
            {
              "pixel_x": 313,
              "pixel_y": 471,
              "depth_raw": 4891,
              "depth_meters": 4.891000232310034
            },
            {
              "pixel_x": 314,
              "pixel_y": 471,
              "depth_raw": 4970,
              "depth_meters": 4.970000236062333
            },
            {
              "pixel_x": 315,
              "pixel_y": 471,
              "depth_raw": 5052,
              "depth_meters": 5.052000239957124
            },
            {
              "pixel_x": 316,
              "pixel_y": 471,
              "depth_raw": 5052,
              "depth_meters": 5.052000239957124
            },
            {
              "pixel_x": 307,
              "pixel_y": 472,
              "depth_raw": 4741,
              "depth_meters": 4.741000225185417
            },
            {
              "pixel_x": 308,
              "pixel_y": 472,
              "depth_raw": 4705,
              "depth_meters": 4.705000223475508
            },
            {
              "pixel_x": 309,
              "pixel_y": 472,
              "depth_raw": 4705,
              "depth_meters": 4.705000223475508
            },
            {
              "pixel_x": 310,
              "pixel_y": 472,
              "depth_raw": 4705,
              "depth_meters": 4.705000223475508
            },
            {
              "pixel_x": 311,
              "pixel_y": 472,
              "depth_raw": 4815,
              "depth_meters": 4.815000228700228
            },
            {
              "pixel_x": 312,
              "pixel_y": 472,
              "depth_raw": 4815,
              "depth_meters": 4.815000228700228
            },
            {
              "pixel_x": 313,
              "pixel_y": 472,
              "depth_raw": 4815,
              "depth_meters": 4.815000228700228
            },
            {
              "pixel_x": 314,
              "pixel_y": 472,
              "depth_raw": 4891,
              "depth_meters": 4.891000232310034
            },
            {
              "pixel_x": 315,
              "pixel_y": 472,
              "depth_raw": 4970,
              "depth_meters": 4.970000236062333
            },
            {
              "pixel_x": 316,
              "pixel_y": 472,
              "depth_raw": 4970,
              "depth_meters": 4.970000236062333
            },
            {
              "pixel_x": 307,
              "pixel_y": 473,
              "depth_raw": 4669,
              "depth_meters": 4.6690002217656
            },
            {
              "pixel_x": 308,
              "pixel_y": 473,
              "depth_raw": 4705,
              "depth_meters": 4.705000223475508
            },
            {
              "pixel_x": 309,
              "pixel_y": 473,
              "depth_raw": 4705,
              "depth_meters": 4.705000223475508
            },
            {
              "pixel_x": 310,
              "pixel_y": 473,
              "depth_raw": 4705,
              "depth_meters": 4.705000223475508
            },
            {
              "pixel_x": 311,
              "pixel_y": 473,
              "depth_raw": 4815,
              "depth_meters": 4.815000228700228
            },
            {
              "pixel_x": 312,
              "pixel_y": 473,
              "depth_raw": 4815,
              "depth_meters": 4.815000228700228
            },
            {
              "pixel_x": 313,
              "pixel_y": 473,
              "depth_raw": 4815,
              "depth_meters": 4.815000228700228
            },
            {
              "pixel_x": 314,
              "pixel_y": 473,
              "depth_raw": 4891,
              "depth_meters": 4.891000232310034
            },
            {
              "pixel_x": 315,
              "pixel_y": 473,
              "depth_raw": 4970,
              "depth_meters": 4.970000236062333
            },
            {
              "pixel_x": 316,
              "pixel_y": 473,
              "depth_raw": 4970,
              "depth_meters": 4.970000236062333
            },
            {
              "pixel_x": 307,
              "pixel_y": 474,
              "depth_raw": 4565,
              "depth_meters": 4.565000216825865
            },
            {
              "pixel_x": 308,
              "pixel_y": 474,
              "depth_raw": 4565,
              "depth_meters": 4.565000216825865
            },
            {
              "pixel_x": 309,
              "pixel_y": 474,
              "depth_raw": 4705,
              "depth_meters": 4.705000223475508
            },
            {
              "pixel_x": 310,
              "pixel_y": 474,
              "depth_raw": 4705,
              "depth_meters": 4.705000223475508
            },
            {
              "pixel_x": 311,
              "pixel_y": 474,
              "depth_raw": 4705,
              "depth_meters": 4.705000223475508
            },
            {
              "pixel_x": 312,
              "pixel_y": 474,
              "depth_raw": 4705,
              "depth_meters": 4.705000223475508
            },
            {
              "pixel_x": 313,
              "pixel_y": 474,
              "depth_raw": 4705,
              "depth_meters": 4.705000223475508
            },
            {
              "pixel_x": 314,
              "pixel_y": 474,
              "depth_raw": 4778,
              "depth_meters": 4.778000226942822
            },
            {
              "pixel_x": 315,
              "pixel_y": 474,
              "depth_raw": 4778,
              "depth_meters": 4.778000226942822
            },
            {
              "pixel_x": 316,
              "pixel_y": 474,
              "depth_raw": 4815,
              "depth_meters": 4.815000228700228
            },
            {
              "pixel_x": 307,
              "pixel_y": 475,
              "depth_raw": 4565,
              "depth_meters": 4.565000216825865
            },
            {
              "pixel_x": 308,
              "pixel_y": 475,
              "depth_raw": 4565,
              "depth_meters": 4.565000216825865
            },
            {
              "pixel_x": 309,
              "pixel_y": 475,
              "depth_raw": 0,
              "depth_meters": 0.0
            },
            {
              "pixel_x": 310,
              "pixel_y": 475,
              "depth_raw": 0,
              "depth_meters": 0.0
            },
            {
              "pixel_x": 311,
              "pixel_y": 475,
              "depth_raw": 4705,
              "depth_meters": 4.705000223475508
            },
            {
              "pixel_x": 312,
              "pixel_y": 475,
              "depth_raw": 4705,
              "depth_meters": 4.705000223475508
            },
            {
              "pixel_x": 313,
              "pixel_y": 475,
              "depth_raw": 4705,
              "depth_meters": 4.705000223475508
            },
            {
              "pixel_x": 314,
              "pixel_y": 475,
              "depth_raw": 4778,
              "depth_meters": 4.778000226942822
            },
            {
              "pixel_x": 315,
              "pixel_y": 475,
              "depth_raw": 4741,
              "depth_meters": 4.741000225185417
            },
            {
              "pixel_x": 316,
              "pixel_y": 475,
              "depth_raw": 4741,
              "depth_meters": 4.741000225185417
            }
          ],
          "depth_scale_used": 0.0010000000474974513,
          "bounding_box_depth": {
            "roi_shape": [
              14,
              10
            ],
            "mean_raw": 5565.108695652174,
            "median_raw": 5406.0
          }
        }
      }
    }
  ]
}