{
  "sample_id": "sample_2660_20250530_153045_524",
  "timestamp": "20250530_153045_524",
  "sample_count": 2660,
  "session_start": "2025-05-30T15:22:04.397580",
  "camera_info": {
    "width": 640,
    "height": 480,
    "depth_scale": 0.0010000000474974513,
    "origin_x": 320,
    "origin_y": 240
  },
  "files": {
    "color_image": "sample_2660_20250530_153045_524.jpg",
    "depth_data": "sample_2660_20250530_153045_524_depth.npy"
  },
  "detections": [
    {
      "detection_id": 0,
      "class_id": 1,
      "confidence": 0.8769832849502563,
      "bounding_box": {
        "x1": 166,
        "y1": 413,
        "x2": 173,
        "y2": 422,
        "center_x": 169,
        "center_y": 417,
        "width": 7,
        "height": 9
      },
      "relative_coordinates": {
        "rel_x": -151.0,
        "rel_y": 177.0
      },
      "depth_information": {
        "statistics": {
          "mean_depth": 7.563524168771913,
          "median_depth": 7.516000356990844,
          "min_depth": 7.251000344404019,
          "max_depth": 8.218000390334055,
          "std_depth": 0.26970401617895795,
          "valid_pixels": 63,
          "total_pixels": 63,
          "fill_ratio": 1.0
        },
        "realsense_depth_data": {
          "center_point": {
            "pixel_x": 169,
            "pixel_y": 417,
            "depth_raw": 7516,
            "depth_meters": 7.516000356990844
          },
          "sample_points": [
            {
              "pixel_x": 166,
              "pixel_y": 413,
              "depth_raw": 8004,
              "depth_meters": 8.0040003801696
            },
            {
              "pixel_x": 167,
              "pixel_y": 413,
              "depth_raw": 8004,
              "depth_meters": 8.0040003801696
            },
            {
              "pixel_x": 168,
              "pixel_y": 413,
              "depth_raw": 8004,
              "depth_meters": 8.0040003801696
            },
            {
              "pixel_x": 169,
              "pixel_y": 413,
              "depth_raw": 8109,
              "depth_meters": 8.109000385156833
            },
            {
              "pixel_x": 170,
              "pixel_y": 413,
              "depth_raw": 8109,
              "depth_meters": 8.109000385156833
            },
            {
              "pixel_x": 171,
              "pixel_y": 413,
              "depth_raw": 8109,
              "depth_meters": 8.109000385156833
            },
            {
              "pixel_x": 172,
              "pixel_y": 413,
              "depth_raw": 8218,
              "depth_meters": 8.218000390334055
            },
            {
              "pixel_x": 166,
              "pixel_y": 414,
              "depth_raw": 7801,
              "depth_meters": 7.801000370527618
            },
            {
              "pixel_x": 167,
              "pixel_y": 414,
              "depth_raw": 7801,
              "depth_meters": 7.801000370527618
            },
            {
              "pixel_x": 168,
              "pixel_y": 414,
              "depth_raw": 7801,
              "depth_meters": 7.801000370527618
            },
            {
              "pixel_x": 169,
              "pixel_y": 414,
              "depth_raw": 7801,
              "depth_meters": 7.801000370527618
            },
            {
              "pixel_x": 170,
              "pixel_y": 414,
              "depth_raw": 7901,
              "depth_meters": 7.901000375277363
            },
            {
              "pixel_x": 171,
              "pixel_y": 414,
              "depth_raw": 7901,
              "depth_meters": 7.901000375277363
            },
            {
              "pixel_x": 172,
              "pixel_y": 414,
              "depth_raw": 8004,
              "depth_meters": 8.0040003801696
            },
            {
              "pixel_x": 166,
              "pixel_y": 415,
              "depth_raw": 7704,
              "depth_meters": 7.704000365920365
            },
            {
              "pixel_x": 167,
              "pixel_y": 415,
              "depth_raw": 7704,
              "depth_meters": 7.704000365920365
            },
            {
              "pixel_x": 168,
              "pixel_y": 415,
              "depth_raw": 7609,
              "depth_meters": 7.609000361408107
            },
            {
              "pixel_x": 169,
              "pixel_y": 415,
              "depth_raw": 7609,
              "depth_meters": 7.609000361408107
            },
            {
              "pixel_x": 170,
              "pixel_y": 415,
              "depth_raw": 7609,
              "depth_meters": 7.609000361408107
            },
            {
              "pixel_x": 171,
              "pixel_y": 415,
              "depth_raw": 7609,
              "depth_meters": 7.609000361408107
            },
            {
              "pixel_x": 172,
              "pixel_y": 415,
              "depth_raw": 7704,
              "depth_meters": 7.704000365920365
            },
            {
              "pixel_x": 166,
              "pixel_y": 416,
              "depth_raw": 7704,
              "depth_meters": 7.704000365920365
            },
            {
              "pixel_x": 167,
              "pixel_y": 416,
              "depth_raw": 7704,
              "depth_meters": 7.704000365920365
            },
            {
              "pixel_x": 168,
              "pixel_y": 416,
              "depth_raw": 7609,
              "depth_meters": 7.609000361408107
            },
            {
              "pixel_x": 169,
              "pixel_y": 416,
              "depth_raw": 7609,
              "depth_meters": 7.609000361408107
            },
            {
              "pixel_x": 170,
              "pixel_y": 416,
              "depth_raw": 7609,
              "depth_meters": 7.609000361408107
            },
            {
              "pixel_x": 171,
              "pixel_y": 416,
              "depth_raw": 7609,
              "depth_meters": 7.609000361408107
            },
            {
              "pixel_x": 172,
              "pixel_y": 416,
              "depth_raw": 7704,
              "depth_meters": 7.704000365920365
            },
            {
              "pixel_x": 166,
              "pixel_y": 417,
              "depth_raw": 7516,
              "depth_meters": 7.516000356990844
            },
            {
              "pixel_x": 167,
              "pixel_y": 417,
              "depth_raw": 7516,
              "depth_meters": 7.516000356990844
            },
            {
              "pixel_x": 168,
              "pixel_y": 417,
              "depth_raw": 7516,
              "depth_meters": 7.516000356990844
            },
            {
              "pixel_x": 169,
              "pixel_y": 417,
              "depth_raw": 7516,
              "depth_meters": 7.516000356990844
            },
            {
              "pixel_x": 170,
              "pixel_y": 417,
              "depth_raw": 7516,
              "depth_meters": 7.516000356990844
            },
            {
              "pixel_x": 171,
              "pixel_y": 417,
              "depth_raw": 7516,
              "depth_meters": 7.516000356990844
            },
            {
              "pixel_x": 172,
              "pixel_y": 417,
              "depth_raw": 7516,
              "depth_meters": 7.516000356990844
            },
            {
              "pixel_x": 166,
              "pixel_y": 418,
              "depth_raw": 7516,
              "depth_meters": 7.516000356990844
            },
            {
              "pixel_x": 167,
              "pixel_y": 418,
              "depth_raw": 7516,
              "depth_meters": 7.516000356990844
            },
            {
              "pixel_x": 168,
              "pixel_y": 418,
              "depth_raw": 7516,
              "depth_meters": 7.516000356990844
            },
            {
              "pixel_x": 169,
              "pixel_y": 418,
              "depth_raw": 7516,
              "depth_meters": 7.516000356990844
            },
            {
              "pixel_x": 170,
              "pixel_y": 418,
              "depth_raw": 7516,
              "depth_meters": 7.516000356990844
            },
            {
              "pixel_x": 171,
              "pixel_y": 418,
              "depth_raw": 7516,
              "depth_meters": 7.516000356990844
            },
            {
              "pixel_x": 172,
              "pixel_y": 418,
              "depth_raw": 7516,
              "depth_meters": 7.516000356990844
            },
            {
              "pixel_x": 166,
              "pixel_y": 419,
              "depth_raw": 7337,
              "depth_meters": 7.3370003484888
            },
            {
              "pixel_x": 167,
              "pixel_y": 419,
              "depth_raw": 7337,
              "depth_meters": 7.3370003484888
            },
            {
              "pixel_x": 168,
              "pixel_y": 419,
              "depth_raw": 7337,
              "depth_meters": 7.3370003484888
            },
            {
              "pixel_x": 169,
              "pixel_y": 419,
              "depth_raw": 7251,
              "depth_meters": 7.251000344404019
            },
            {
              "pixel_x": 170,
              "pixel_y": 419,
              "depth_raw": 7251,
              "depth_meters": 7.251000344404019
            },
            {
              "pixel_x": 171,
              "pixel_y": 419,
              "depth_raw": 7251,
              "depth_meters": 7.251000344404019
            },
            {
              "pixel_x": 172,
              "pixel_y": 419,
              "depth_raw": 7337,
              "depth_meters": 7.3370003484888
            },
            {
              "pixel_x": 166,
              "pixel_y": 420,
              "depth_raw": 7251,
              "depth_meters": 7.251000344404019
            },
            {
              "pixel_x": 167,
              "pixel_y": 420,
              "depth_raw": 7251,
              "depth_meters": 7.251000344404019
            },
            {
              "pixel_x": 168,
              "pixel_y": 420,
              "depth_raw": 7251,
              "depth_meters": 7.251000344404019
            },
            {
              "pixel_x": 169,
              "pixel_y": 420,
              "depth_raw": 7251,
              "depth_meters": 7.251000344404019
            },
            {
              "pixel_x": 170,
              "pixel_y": 420,
              "depth_raw": 7251,
              "depth_meters": 7.251000344404019
            },
            {
              "pixel_x": 171,
              "pixel_y": 420,
              "depth_raw": 7251,
              "depth_meters": 7.251000344404019
            },
            {
              "pixel_x": 172,
              "pixel_y": 420,
              "depth_raw": 7251,
              "depth_meters": 7.251000344404019
            },
            {
              "pixel_x": 166,
              "pixel_y": 421,
              "depth_raw": 7251,
              "depth_meters": 7.251000344404019
            },
            {
              "pixel_x": 167,
              "pixel_y": 421,
              "depth_raw": 7251,
              "depth_meters": 7.251000344404019
            },
            {
              "pixel_x": 168,
              "pixel_y": 421,
              "depth_raw": 7251,
              "depth_meters": 7.251000344404019
            },
            {
              "pixel_x": 169,
              "pixel_y": 421,
              "depth_raw": 7251,
              "depth_meters": 7.251000344404019
            },
            {
              "pixel_x": 170,
              "pixel_y": 421,
              "depth_raw": 7251,
              "depth_meters": 7.251000344404019
            },
            {
              "pixel_x": 171,
              "pixel_y": 421,
              "depth_raw": 7251,
              "depth_meters": 7.251000344404019
            },
            {
              "pixel_x": 172,
              "pixel_y": 421,
              "depth_raw": 7251,
              "depth_meters": 7.251000344404019
            }
          ],
          "depth_scale_used": 0.0010000000474974513,
          "bounding_box_depth": {
            "roi_shape": [
              9,
              7
            ],
            "mean_raw": 7563.523809523809,
            "median_raw": 7516.0
          }
        }
      }
    },
    {
      "detection_id": 1,
      "class_id": 1,
      "confidence": 0.8022235631942749,
      "bounding_box": {
        "x1": 318,
        "y1": 410,
        "x2": 325,
        "y2": 420,
        "center_x": 321,
        "center_y": 415,
        "width": 7,
        "height": 10
      },
      "relative_coordinates": {
        "rel_x": 1.0,
        "rel_y": 175.0
      },
      "depth_information": {
        "statistics": {
          "mean_depth": 18.76622311356995,
          "median_depth": 17.60900083638262,
          "min_depth": 12.326000585453585,
          "max_depth": 24.653001170954667,
          "std_depth": 3.3776480197732637,
          "valid_pixels": 36,
          "total_pixels": 70,
          "fill_ratio": 0.5142857142857142
        },
        "realsense_depth_data": {
          "center_point": {
            "pixel_x": 321,
            "pixel_y": 415,
            "depth_raw": 0,
            "depth_meters": 0.0
          },
          "sample_points": [
            {
              "pixel_x": 318,
              "pixel_y": 410,
              "depth_raw": 22827,
              "depth_meters": 22.82700108422432
            },
            {
              "pixel_x": 319,
              "pixel_y": 410,
              "depth_raw": 22827,
              "depth_meters": 22.82700108422432
            },
            {
              "pixel_x": 320,
              "pixel_y": 410,
              "depth_raw": 22827,
              "depth_meters": 22.82700108422432
            },
            {
              "pixel_x": 321,
              "pixel_y": 410,
              "depth_raw": 23704,
              "depth_meters": 23.704001125879586
            },
            {
              "pixel_x": 322,
              "pixel_y": 410,
              "depth_raw": 24653,
              "depth_meters": 24.653001170954667
            },
            {
              "pixel_x": 323,
              "pixel_y": 410,
              "depth_raw": 23704,
              "depth_meters": 23.704001125879586
            },
            {
              "pixel_x": 324,
              "pixel_y": 410,
              "depth_raw": 22011,
              "depth_meters": 22.0110010454664
            },
            {
              "pixel_x": 318,
              "pixel_y": 411,
              "depth_raw": 20544,
              "depth_meters": 20.54400097578764
            },
            {
              "pixel_x": 319,
              "pixel_y": 411,
              "depth_raw": 20544,
              "depth_meters": 20.54400097578764
            },
            {
              "pixel_x": 320,
              "pixel_y": 411,
              "depth_raw": 20544,
              "depth_meters": 20.54400097578764
            },
            {
              "pixel_x": 321,
              "pixel_y": 411,
              "depth_raw": 20544,
              "depth_meters": 20.54400097578764
            },
            {
              "pixel_x": 322,
              "pixel_y": 411,
              "depth_raw": 22011,
              "depth_meters": 22.0110010454664
            },
            {
              "pixel_x": 323,
              "pixel_y": 411,
              "depth_raw": 22011,
              "depth_meters": 22.0110010454664
            },
            {
              "pixel_x": 324,
              "pixel_y": 411,
              "depth_raw": 21252,
              "depth_meters": 21.252001009415835
            },
            {
              "pixel_x": 318,
              "pixel_y": 412,
              "depth_raw": 17609,
              "depth_meters": 17.60900083638262
            },
            {
              "pixel_x": 319,
              "pixel_y": 412,
              "depth_raw": 17609,
              "depth_meters": 17.60900083638262
            },
            {
              "pixel_x": 320,
              "pixel_y": 412,
              "depth_raw": 17120,
              "depth_meters": 17.120000813156366
            },
            {
              "pixel_x": 321,
              "pixel_y": 412,
              "depth_raw": 17120,
              "depth_meters": 17.120000813156366
            },
            {
              "pixel_x": 322,
              "pixel_y": 412,
              "depth_raw": 22011,
              "depth_meters": 22.0110010454664
            },
            {
              "pixel_x": 323,
              "pixel_y": 412,
              "depth_raw": 22011,
              "depth_meters": 22.0110010454664
            },
            {
              "pixel_x": 324,
              "pixel_y": 412,
              "depth_raw": 17609,
              "depth_meters": 17.60900083638262
            },
            {
              "pixel_x": 318,
              "pixel_y": 413,
              "depth_raw": 17609,
              "depth_meters": 17.60900083638262
            },
            {
              "pixel_x": 319,
              "pixel_y": 413,
              "depth_raw": 17609,
              "depth_meters": 17.60900083638262
            },
            {
              "pixel_x": 320,
              "pixel_y": 413,
              "depth_raw": 17120,
              "depth_meters": 17.120000813156366
            },
            {
              "pixel_x": 321,
              "pixel_y": 413,
              "depth_raw": 17120,
              "depth_meters": 17.120000813156366
            },
            {
              "pixel_x": 322,
              "pixel_y": 413,
              "depth_raw": 0,
              "depth_meters": 0.0
            },
            {
              "pixel_x": 323,
              "pixel_y": 413,
              "depth_raw": 0,
              "depth_meters": 0.0
            },
            {
              "pixel_x": 324,
              "pixel_y": 413,
              "depth_raw": 17609,
              "depth_meters": 17.60900083638262
            },
            {
              "pixel_x": 318,
              "pixel_y": 414,
              "depth_raw": 14674,
              "depth_meters": 14.6740006969776
            },
            {
              "pixel_x": 319,
              "pixel_y": 414,
              "depth_raw": 14674,
              "depth_meters": 14.6740006969776
            },
            {
              "pixel_x": 320,
              "pixel_y": 414,
              "depth_raw": 14674,
              "depth_meters": 14.6740006969776
            },
            {
              "pixel_x": 321,
              "pixel_y": 414,
              "depth_raw": 17120,
              "depth_meters": 17.120000813156366
            },
            {
              "pixel_x": 322,
              "pixel_y": 414,
              "depth_raw": 0,
              "depth_meters": 0.0
            },
            {
              "pixel_x": 323,
              "pixel_y": 414,
              "depth_raw": 0,
              "depth_meters": 0.0
            },
            {
              "pixel_x": 324,
              "pixel_y": 414,
              "depth_raw": 17609,
              "depth_meters": 17.60900083638262
            },
            {
              "pixel_x": 318,
              "pixel_y": 415,
              "depth_raw": 14674,
              "depth_meters": 14.6740006969776
            },
            {
              "pixel_x": 319,
              "pixel_y": 415,
              "depth_raw": 14674,
              "depth_meters": 14.6740006969776
            },
            {
              "pixel_x": 320,
              "pixel_y": 415,
              "depth_raw": 14674,
              "depth_meters": 14.6740006969776
            },
            {
              "pixel_x": 321,
              "pixel_y": 415,
              "depth_raw": 0,
              "depth_meters": 0.0
            },
            {
              "pixel_x": 322,
              "pixel_y": 415,
              "depth_raw": 0,
              "depth_meters": 0.0
            },
            {
              "pixel_x": 323,
              "pixel_y": 415,
              "depth_raw": 0,
              "depth_meters": 0.0
            },
            {
              "pixel_x": 324,
              "pixel_y": 415,
              "depth_raw": 0,
              "depth_meters": 0.0
            },
            {
              "pixel_x": 318,
              "pixel_y": 416,
              "depth_raw": 12326,
              "depth_meters": 12.326000585453585
            },
            {
              "pixel_x": 319,
              "pixel_y": 416,
              "depth_raw": 0,
              "depth_meters": 0.0
            },
            {
              "pixel_x": 320,
              "pixel_y": 416,
              "depth_raw": 0,
              "depth_meters": 0.0
            },
            {
              "pixel_x": 321,
              "pixel_y": 416,
              "depth_raw": 0,
              "depth_meters": 0.0
            },
            {
              "pixel_x": 322,
              "pixel_y": 416,
              "depth_raw": 0,
              "depth_meters": 0.0
            },
            {
              "pixel_x": 323,
              "pixel_y": 416,
              "depth_raw": 0,
              "depth_meters": 0.0
            },
            {
              "pixel_x": 324,
              "pixel_y": 416,
              "depth_raw": 0,
              "depth_meters": 0.0
            },
            {
              "pixel_x": 318,
              "pixel_y": 417,
              "depth_raw": 12326,
              "depth_meters": 12.326000585453585
            },
            {
              "pixel_x": 319,
              "pixel_y": 417,
              "depth_raw": 0,
              "depth_meters": 0.0
            },
            {
              "pixel_x": 320,
              "pixel_y": 417,
              "depth_raw": 0,
              "depth_meters": 0.0
            },
            {
              "pixel_x": 321,
              "pixel_y": 417,
              "depth_raw": 0,
              "depth_meters": 0.0
            },
            {
              "pixel_x": 322,
              "pixel_y": 417,
              "depth_raw": 0,
              "depth_meters": 0.0
            },
            {
              "pixel_x": 323,
              "pixel_y": 417,
              "depth_raw": 0,
              "depth_meters": 0.0
            },
            {
              "pixel_x": 324,
              "pixel_y": 417,
              "depth_raw": 0,
              "depth_meters": 0.0
            },
            {
              "pixel_x": 318,
              "pixel_y": 418,
              "depth_raw": 0,
              "depth_meters": 0.0
            },
            {
              "pixel_x": 319,
              "pixel_y": 418,
              "depth_raw": 0,
              "depth_meters": 0.0
            },
            {
              "pixel_x": 320,
              "pixel_y": 418,
              "depth_raw": 0,
              "depth_meters": 0.0
            },
            {
              "pixel_x": 321,
              "pixel_y": 418,
              "depth_raw": 0,
              "depth_meters": 0.0
            },
            {
              "pixel_x": 322,
              "pixel_y": 418,
              "depth_raw": 0,
              "depth_meters": 0.0
            },
            {
              "pixel_x": 323,
              "pixel_y": 418,
              "depth_raw": 0,
              "depth_meters": 0.0
            },
            {
              "pixel_x": 324,
              "pixel_y": 418,
              "depth_raw": 0,
              "depth_meters": 0.0
            },
            {
              "pixel_x": 318,
              "pixel_y": 419,
              "depth_raw": 0,
              "depth_meters": 0.0
            },
            {
              "pixel_x": 319,
              "pixel_y": 419,
              "depth_raw": 0,
              "depth_meters": 0.0
            },
            {
              "pixel_x": 320,
              "pixel_y": 419,
              "depth_raw": 0,
              "depth_meters": 0.0
            },
            {
              "pixel_x": 321,
              "pixel_y": 419,
              "depth_raw": 0,
              "depth_meters": 0.0
            },
            {
              "pixel_x": 322,
              "pixel_y": 419,
              "depth_raw": 0,
              "depth_meters": 0.0
            },
            {
              "pixel_x": 323,
              "pixel_y": 419,
              "depth_raw": 0,
              "depth_meters": 0.0
            },
            {
              "pixel_x": 324,
              "pixel_y": 419,
              "depth_raw": 0,
              "depth_meters": 0.0
            }
          ],
          "depth_scale_used": 0.0010000000474974513,
          "bounding_box_depth": {
            "roi_shape": [
              10,
              7
            ],
            "mean_raw": 18766.222222222223,
            "median_raw": 17609.0
          }
        }
      }
    },
    {
      "detection_id": 2,
      "class_id": 1,
      "confidence": 0.7744759321212769,
      "bounding_box": {
        "x1": 363,
        "y1": 411,
        "x2": 370,
        "y2": 421,
        "center_x": 366,
        "center_y": 416,
        "width": 7,
        "height": 10
      },
      "relative_coordinates": {
        "rel_x": 46.0,
        "rel_y": 176.0
      },
      "depth_information": {
        "statistics": {
          "mean_depth": 9.374100445245858,
          "median_depth": 9.199000436929055,
          "min_depth": 7.426000352716073,
          "max_depth": 12.578000597422943,
          "std_depth": 1.2939891114258915,
          "valid_pixels": 70,
          "total_pixels": 70,
          "fill_ratio": 1.0
        },
        "realsense_depth_data": {
          "center_point": {
            "pixel_x": 366,
            "pixel_y": 416,
            "depth_raw": 8560,
            "depth_meters": 8.560000406578183
          },
          "sample_points": [
            {
              "pixel_x": 363,
              "pixel_y": 411,
              "depth_raw": 12578,
              "depth_meters": 12.578000597422943
            },
            {
              "pixel_x": 364,
              "pixel_y": 411,
              "depth_raw": 11629,
              "depth_meters": 11.629000552347861
            },
            {
              "pixel_x": 365,
              "pixel_y": 411,
              "depth_raw": 11629,
              "depth_meters": 11.629000552347861
            },
            {
              "pixel_x": 366,
              "pixel_y": 411,
              "depth_raw": 10813,
              "depth_meters": 10.813000513589941
            },
            {
              "pixel_x": 367,
              "pixel_y": 411,
              "depth_raw": 10272,
              "depth_meters": 10.27200048789382
            },
            {
              "pixel_x": 368,
              "pixel_y": 411,
              "depth_raw": 10272,
              "depth_meters": 10.27200048789382
            },
            {
              "pixel_x": 369,
              "pixel_y": 411,
              "depth_raw": 10272,
              "depth_meters": 10.27200048789382
            },
            {
              "pixel_x": 363,
              "pixel_y": 412,
              "depth_raw": 12578,
              "depth_meters": 12.578000597422943
            },
            {
              "pixel_x": 364,
              "pixel_y": 412,
              "depth_raw": 11629,
              "depth_meters": 11.629000552347861
            },
            {
              "pixel_x": 365,
              "pixel_y": 412,
              "depth_raw": 11629,
              "depth_meters": 11.629000552347861
            },
            {
              "pixel_x": 366,
              "pixel_y": 412,
              "depth_raw": 10813,
              "depth_meters": 10.813000513589941
            },
            {
              "pixel_x": 367,
              "pixel_y": 412,
              "depth_raw": 10272,
              "depth_meters": 10.27200048789382
            },
            {
              "pixel_x": 368,
              "pixel_y": 412,
              "depth_raw": 10272,
              "depth_meters": 10.27200048789382
            },
            {
              "pixel_x": 369,
              "pixel_y": 412,
              "depth_raw": 10272,
              "depth_meters": 10.27200048789382
            },
            {
              "pixel_x": 363,
              "pixel_y": 413,
              "depth_raw": 11413,
              "depth_meters": 11.413000542088412
            },
            {
              "pixel_x": 364,
              "pixel_y": 413,
              "depth_raw": 10626,
              "depth_meters": 10.626000504707918
            },
            {
              "pixel_x": 365,
              "pixel_y": 413,
              "depth_raw": 10626,
              "depth_meters": 10.626000504707918
            },
            {
              "pixel_x": 366,
              "pixel_y": 413,
              "depth_raw": 9783,
              "depth_meters": 9.783000464667566
            },
            {
              "pixel_x": 367,
              "pixel_y": 413,
              "depth_raw": 9482,
              "depth_meters": 9.482000450370833
            },
            {
              "pixel_x": 368,
              "pixel_y": 413,
              "depth_raw": 9482,
              "depth_meters": 9.482000450370833
            },
            {
              "pixel_x": 369,
              "pixel_y": 413,
              "depth_raw": 9482,
              "depth_meters": 9.482000450370833
            },
            {
              "pixel_x": 363,
              "pixel_y": 414,
              "depth_raw": 11413,
              "depth_meters": 11.413000542088412
            },
            {
              "pixel_x": 364,
              "pixel_y": 414,
              "depth_raw": 10626,
              "depth_meters": 10.626000504707918
            },
            {
              "pixel_x": 365,
              "pixel_y": 414,
              "depth_raw": 10626,
              "depth_meters": 10.626000504707918
            },
            {
              "pixel_x": 366,
              "pixel_y": 414,
              "depth_raw": 9783,
              "depth_meters": 9.783000464667566
            },
            {
              "pixel_x": 367,
              "pixel_y": 414,
              "depth_raw": 9482,
              "depth_meters": 9.482000450370833
            },
            {
              "pixel_x": 368,
              "pixel_y": 414,
              "depth_raw": 9482,
              "depth_meters": 9.482000450370833
            },
            {
              "pixel_x": 369,
              "pixel_y": 414,
              "depth_raw": 8932,
              "depth_meters": 8.932000424247235
            },
            {
              "pixel_x": 363,
              "pixel_y": 415,
              "depth_raw": 10626,
              "depth_meters": 10.626000504707918
            },
            {
              "pixel_x": 364,
              "pixel_y": 415,
              "depth_raw": 9783,
              "depth_meters": 9.783000464667566
            },
            {
              "pixel_x": 365,
              "pixel_y": 415,
              "depth_raw": 9783,
              "depth_meters": 9.783000464667566
            },
            {
              "pixel_x": 366,
              "pixel_y": 415,
              "depth_raw": 9063,
              "depth_meters": 9.063000430469401
            },
            {
              "pixel_x": 367,
              "pixel_y": 415,
              "depth_raw": 9063,
              "depth_meters": 9.063000430469401
            },
            {
              "pixel_x": 368,
              "pixel_y": 415,
              "depth_raw": 8681,
              "depth_meters": 8.681000412325375
            },
            {
              "pixel_x": 369,
              "pixel_y": 415,
              "depth_raw": 8681,
              "depth_meters": 8.681000412325375
            },
            {
              "pixel_x": 363,
              "pixel_y": 416,
              "depth_raw": 9941,
              "depth_meters": 9.941000472172163
            },
            {
              "pixel_x": 364,
              "pixel_y": 416,
              "depth_raw": 9199,
              "depth_meters": 9.199000436929055
            },
            {
              "pixel_x": 365,
              "pixel_y": 416,
              "depth_raw": 9199,
              "depth_meters": 9.199000436929055
            },
            {
              "pixel_x": 366,
              "pixel_y": 416,
              "depth_raw": 8560,
              "depth_meters": 8.560000406578183
            },
            {
              "pixel_x": 367,
              "pixel_y": 416,
              "depth_raw": 8560,
              "depth_meters": 8.560000406578183
            },
            {
              "pixel_x": 368,
              "pixel_y": 416,
              "depth_raw": 8218,
              "depth_meters": 8.218000390334055
            },
            {
              "pixel_x": 369,
              "pixel_y": 416,
              "depth_raw": 8218,
              "depth_meters": 8.218000390334055
            },
            {
              "pixel_x": 363,
              "pixel_y": 417,
              "depth_raw": 9941,
              "depth_meters": 9.941000472172163
            },
            {
              "pixel_x": 364,
              "pixel_y": 417,
              "depth_raw": 9199,
              "depth_meters": 9.199000436929055
            },
            {
              "pixel_x": 365,
              "pixel_y": 417,
              "depth_raw": 9199,
              "depth_meters": 9.199000436929055
            },
            {
              "pixel_x": 366,
              "pixel_y": 417,
              "depth_raw": 8560,
              "depth_meters": 8.560000406578183
            },
            {
              "pixel_x": 367,
              "pixel_y": 417,
              "depth_raw": 8560,
              "depth_meters": 8.560000406578183
            },
            {
              "pixel_x": 368,
              "pixel_y": 417,
              "depth_raw": 8218,
              "depth_meters": 8.218000390334055
            },
            {
              "pixel_x": 369,
              "pixel_y": 417,
              "depth_raw": 8218,
              "depth_meters": 8.218000390334055
            },
            {
              "pixel_x": 363,
              "pixel_y": 418,
              "depth_raw": 9338,
              "depth_meters": 9.3380004435312
            },
            {
              "pixel_x": 364,
              "pixel_y": 418,
              "depth_raw": 8681,
              "depth_meters": 8.681000412325375
            },
            {
              "pixel_x": 365,
              "pixel_y": 418,
              "depth_raw": 8681,
              "depth_meters": 8.681000412325375
            },
            {
              "pixel_x": 366,
              "pixel_y": 418,
              "depth_raw": 8004,
              "depth_meters": 8.0040003801696
            },
            {
              "pixel_x": 367,
              "pixel_y": 418,
              "depth_raw": 8004,
              "depth_meters": 8.0040003801696
            },
            {
              "pixel_x": 368,
              "pixel_y": 418,
              "depth_raw": 7704,
              "depth_meters": 7.704000365920365
            },
            {
              "pixel_x": 369,
              "pixel_y": 418,
              "depth_raw": 7704,
              "depth_meters": 7.704000365920365
            },
            {
              "pixel_x": 363,
              "pixel_y": 419,
              "depth_raw": 8932,
              "depth_meters": 8.932000424247235
            },
            {
              "pixel_x": 364,
              "pixel_y": 419,
              "depth_raw": 8681,
              "depth_meters": 8.681000412325375
            },
            {
              "pixel_x": 365,
              "pixel_y": 419,
              "depth_raw": 8218,
              "depth_meters": 8.218000390334055
            },
            {
              "pixel_x": 366,
              "pixel_y": 419,
              "depth_raw": 7704,
              "depth_meters": 7.704000365920365
            },
            {
              "pixel_x": 367,
              "pixel_y": 419,
              "depth_raw": 7704,
              "depth_meters": 7.704000365920365
            },
            {
              "pixel_x": 368,
              "pixel_y": 419,
              "depth_raw": 7426,
              "depth_meters": 7.426000352716073
            },
            {
              "pixel_x": 369,
              "pixel_y": 419,
              "depth_raw": 7426,
              "depth_meters": 7.426000352716073
            },
            {
              "pixel_x": 363,
              "pixel_y": 420,
              "depth_raw": 8932,
              "depth_meters": 8.932000424247235
            },
            {
              "pixel_x": 364,
              "pixel_y": 420,
              "depth_raw": 8932,
              "depth_meters": 8.932000424247235
            },
            {
              "pixel_x": 365,
              "pixel_y": 420,
              "depth_raw": 8218,
              "depth_meters": 8.218000390334055
            },
            {
              "pixel_x": 366,
              "pixel_y": 420,
              "depth_raw": 7704,
              "depth_meters": 7.704000365920365
            },
            {
              "pixel_x": 367,
              "pixel_y": 420,
              "depth_raw": 7704,
              "depth_meters": 7.704000365920365
            },
            {
              "pixel_x": 368,
              "pixel_y": 420,
              "depth_raw": 7426,
              "depth_meters": 7.426000352716073
            },
            {
              "pixel_x": 369,
              "pixel_y": 420,
              "depth_raw": 7426,
              "depth_meters": 7.426000352716073
            }
          ],
          "depth_scale_used": 0.0010000000474974513,
          "bounding_box_depth": {
            "roi_shape": [
              10,
              7
            ],
            "mean_raw": 9374.1,
            "median_raw": 9199.0
          }
        }
      }
    },
    {
      "detection_id": 3,
      "class_id": 0,
      "confidence": 0.7276636362075806,
      "bounding_box": {
        "x1": 413,
        "y1": 411,
        "x2": 420,
        "y2": 421,
        "center_x": 416,
        "center_y": 416,
        "width": 7,
        "height": 10
      },
      "relative_coordinates": {
        "rel_x": 96.0,
        "rel_y": 176.0
      },
      "depth_information": {
        "statistics": {
          "mean_depth": 9.481707346908635,
          "median_depth": 9.783000464667566,
          "min_depth": 7.801000370527618,
          "max_depth": 11.20600053225644,
          "std_depth": 1.0715121955566445,
          "valid_pixels": 58,
          "total_pixels": 70,
          "fill_ratio": 0.8285714285714286
        },
        "realsense_depth_data": {
          "center_point": {
            "pixel_x": 416,
            "pixel_y": 416,
            "depth_raw": 0,
            "depth_meters": 0.0
          },
          "sample_points": [
            {
              "pixel_x": 413,
              "pixel_y": 411,
              "depth_raw": 11206,
              "depth_meters": 11.20600053225644
            },
            {
              "pixel_x": 414,
              "pixel_y": 411,
              "depth_raw": 11006,
              "depth_meters": 11.006000522756949
            },
            {
              "pixel_x": 415,
              "pixel_y": 411,
              "depth_raw": 11006,
              "depth_meters": 11.006000522756949
            },
            {
              "pixel_x": 416,
              "pixel_y": 411,
              "depth_raw": 10813,
              "depth_meters": 10.813000513589941
            },
            {
              "pixel_x": 417,
              "pixel_y": 411,
              "depth_raw": 10813,
              "depth_meters": 10.813000513589941
            },
            {
              "pixel_x": 418,
              "pixel_y": 411,
              "depth_raw": 10813,
              "depth_meters": 10.813000513589941
            },
            {
              "pixel_x": 419,
              "pixel_y": 411,
              "depth_raw": 10813,
              "depth_meters": 10.813000513589941
            },
            {
              "pixel_x": 413,
              "pixel_y": 412,
              "depth_raw": 10626,
              "depth_meters": 10.626000504707918
            },
            {
              "pixel_x": 414,
              "pixel_y": 412,
              "depth_raw": 10626,
              "depth_meters": 10.626000504707918
            },
            {
              "pixel_x": 415,
              "pixel_y": 412,
              "depth_raw": 10446,
              "depth_meters": 10.446000496158376
            },
            {
              "pixel_x": 416,
              "pixel_y": 412,
              "depth_raw": 10272,
              "depth_meters": 10.27200048789382
            },
            {
              "pixel_x": 417,
              "pixel_y": 412,
              "depth_raw": 10272,
              "depth_meters": 10.27200048789382
            },
            {
              "pixel_x": 418,
              "pixel_y": 412,
              "depth_raw": 10104,
              "depth_meters": 10.104000479914248
            },
            {
              "pixel_x": 419,
              "pixel_y": 412,
              "depth_raw": 10104,
              "depth_meters": 10.104000479914248
            },
            {
              "pixel_x": 413,
              "pixel_y": 413,
              "depth_raw": 10626,
              "depth_meters": 10.626000504707918
            },
            {
              "pixel_x": 414,
              "pixel_y": 413,
              "depth_raw": 10626,
              "depth_meters": 10.626000504707918
            },
            {
              "pixel_x": 415,
              "pixel_y": 413,
              "depth_raw": 10446,
              "depth_meters": 10.446000496158376
            },
            {
              "pixel_x": 416,
              "pixel_y": 413,
              "depth_raw": 10272,
              "depth_meters": 10.27200048789382
            },
            {
              "pixel_x": 417,
              "pixel_y": 413,
              "depth_raw": 10272,
              "depth_meters": 10.27200048789382
            },
            {
              "pixel_x": 418,
              "pixel_y": 413,
              "depth_raw": 10104,
              "depth_meters": 10.104000479914248
            },
            {
              "pixel_x": 419,
              "pixel_y": 413,
              "depth_raw": 9783,
              "depth_meters": 9.783000464667566
            },
            {
              "pixel_x": 413,
              "pixel_y": 414,
              "depth_raw": 10272,
              "depth_meters": 10.27200048789382
            },
            {
              "pixel_x": 414,
              "pixel_y": 414,
              "depth_raw": 10272,
              "depth_meters": 10.27200048789382
            },
            {
              "pixel_x": 415,
              "pixel_y": 414,
              "depth_raw": 10104,
              "depth_meters": 10.104000479914248
            },
            {
              "pixel_x": 416,
              "pixel_y": 414,
              "depth_raw": 10104,
              "depth_meters": 10.104000479914248
            },
            {
              "pixel_x": 417,
              "pixel_y": 414,
              "depth_raw": 0,
              "depth_meters": 0.0
            },
            {
              "pixel_x": 418,
              "pixel_y": 414,
              "depth_raw": 0,
              "depth_meters": 0.0
            },
            {
              "pixel_x": 419,
              "pixel_y": 414,
              "depth_raw": 9783,
              "depth_meters": 9.783000464667566
            },
            {
              "pixel_x": 413,
              "pixel_y": 415,
              "depth_raw": 9783,
              "depth_meters": 9.783000464667566
            },
            {
              "pixel_x": 414,
              "pixel_y": 415,
              "depth_raw": 9783,
              "depth_meters": 9.783000464667566
            },
            {
              "pixel_x": 415,
              "pixel_y": 415,
              "depth_raw": 9783,
              "depth_meters": 9.783000464667566
            },
            {
              "pixel_x": 416,
              "pixel_y": 415,
              "depth_raw": 10104,
              "depth_meters": 10.104000479914248
            },
            {
              "pixel_x": 417,
              "pixel_y": 415,
              "depth_raw": 0,
              "depth_meters": 0.0
            },
            {
              "pixel_x": 418,
              "pixel_y": 415,
              "depth_raw": 0,
              "depth_meters": 0.0
            },
            {
              "pixel_x": 419,
              "pixel_y": 415,
              "depth_raw": 9783,
              "depth_meters": 9.783000464667566
            },
            {
              "pixel_x": 413,
              "pixel_y": 416,
              "depth_raw": 9783,
              "depth_meters": 9.783000464667566
            },
            {
              "pixel_x": 414,
              "pixel_y": 416,
              "depth_raw": 9783,
              "depth_meters": 9.783000464667566
            },
            {
              "pixel_x": 415,
              "pixel_y": 416,
              "depth_raw": 9783,
              "depth_meters": 9.783000464667566
            },
            {
              "pixel_x": 416,
              "pixel_y": 416,
              "depth_raw": 0,
              "depth_meters": 0.0
            },
            {
              "pixel_x": 417,
              "pixel_y": 416,
              "depth_raw": 0,
              "depth_meters": 0.0
            },
            {
              "pixel_x": 418,
              "pixel_y": 416,
              "depth_raw": 0,
              "depth_meters": 0.0
            },
            {
              "pixel_x": 419,
              "pixel_y": 416,
              "depth_raw": 0,
              "depth_meters": 0.0
            },
            {
              "pixel_x": 413,
              "pixel_y": 417,
              "depth_raw": 9199,
              "depth_meters": 9.199000436929055
            },
            {
              "pixel_x": 414,
              "pixel_y": 417,
              "depth_raw": 9199,
              "depth_meters": 9.199000436929055
            },
            {
              "pixel_x": 415,
              "pixel_y": 417,
              "depth_raw": 9199,
              "depth_meters": 9.199000436929055
            },
            {
              "pixel_x": 416,
              "pixel_y": 417,
              "depth_raw": 0,
              "depth_meters": 0.0
            },
            {
              "pixel_x": 417,
              "pixel_y": 417,
              "depth_raw": 0,
              "depth_meters": 0.0
            },
            {
              "pixel_x": 418,
              "pixel_y": 417,
              "depth_raw": 0,
              "depth_meters": 0.0
            },
            {
              "pixel_x": 419,
              "pixel_y": 417,
              "depth_raw": 0,
              "depth_meters": 0.0
            },
            {
              "pixel_x": 413,
              "pixel_y": 418,
              "depth_raw": 8805,
              "depth_meters": 8.805000418215059
            },
            {
              "pixel_x": 414,
              "pixel_y": 418,
              "depth_raw": 8805,
              "depth_meters": 8.805000418215059
            },
            {
              "pixel_x": 415,
              "pixel_y": 418,
              "depth_raw": 8329,
              "depth_meters": 8.329000395606272
            },
            {
              "pixel_x": 416,
              "pixel_y": 418,
              "depth_raw": 8329,
              "depth_meters": 8.329000395606272
            },
            {
              "pixel_x": 417,
              "pixel_y": 418,
              "depth_raw": 8004,
              "depth_meters": 8.0040003801696
            },
            {
              "pixel_x": 418,
              "pixel_y": 418,
              "depth_raw": 7801,
              "depth_meters": 7.801000370527618
            },
            {
              "pixel_x": 419,
              "pixel_y": 418,
              "depth_raw": 7801,
              "depth_meters": 7.801000370527618
            },
            {
              "pixel_x": 413,
              "pixel_y": 419,
              "depth_raw": 8805,
              "depth_meters": 8.805000418215059
            },
            {
              "pixel_x": 414,
              "pixel_y": 419,
              "depth_raw": 8805,
              "depth_meters": 8.805000418215059
            },
            {
              "pixel_x": 415,
              "pixel_y": 419,
              "depth_raw": 8329,
              "depth_meters": 8.329000395606272
            },
            {
              "pixel_x": 416,
              "pixel_y": 419,
              "depth_raw": 8329,
              "depth_meters": 8.329000395606272
            },
            {
              "pixel_x": 417,
              "pixel_y": 419,
              "depth_raw": 8004,
              "depth_meters": 8.0040003801696
            },
            {
              "pixel_x": 418,
              "pixel_y": 419,
              "depth_raw": 7801,
              "depth_meters": 7.801000370527618
            },
            {
              "pixel_x": 419,
              "pixel_y": 419,
              "depth_raw": 7801,
              "depth_meters": 7.801000370527618
            },
            {
              "pixel_x": 413,
              "pixel_y": 420,
              "depth_raw": 8560,
              "depth_meters": 8.560000406578183
            },
            {
              "pixel_x": 414,
              "pixel_y": 420,
              "depth_raw": 8560,
              "depth_meters": 8.560000406578183
            },
            {
              "pixel_x": 415,
              "pixel_y": 420,
              "depth_raw": 7901,
              "depth_meters": 7.901000375277363
            },
            {
              "pixel_x": 416,
              "pixel_y": 420,
              "depth_raw": 7901,
              "depth_meters": 7.901000375277363
            },
            {
              "pixel_x": 417,
              "pixel_y": 420,
              "depth_raw": 7901,
              "depth_meters": 7.901000375277363
            },
            {
              "pixel_x": 418,
              "pixel_y": 420,
              "depth_raw": 7801,
              "depth_meters": 7.801000370527618
            },
            {
              "pixel_x": 419,
              "pixel_y": 420,
              "depth_raw": 7801,
              "depth_meters": 7.801000370527618
            }
          ],
          "depth_scale_used": 0.0010000000474974513,
          "bounding_box_depth": {
            "roi_shape": [
              10,
              7
            ],
            "mean_raw": 9481.706896551725,
            "median_raw": 9783.0
          }
        }
      }
    },
    {
      "detection_id": 4,
      "class_id": 0,
      "confidence": 0.7021989822387695,
      "bounding_box": {
        "x1": 216,
        "y1": 412,
        "x2": 223,
        "y2": 422,
        "center_x": 219,
        "center_y": 417,
        "width": 7,
        "height": 10
      },
      "relative_coordinates": {
        "rel_x": -101.0,
        "rel_y": 177.0
      },
      "depth_information": {
        "statistics": {
          "mean_depth": 14.409694232810814,
          "median_depth": 13.04600061965175,
          "min_depth": 7.801000370527618,
          "max_depth": 29.3480013939552,
          "std_depth": 5.680340189175842,
          "valid_pixels": 62,
          "total_pixels": 70,
          "fill_ratio": 0.8857142857142857
        },
        "realsense_depth_data": {
          "center_point": {
            "pixel_x": 219,
            "pixel_y": 417,
            "depth_raw": 12085,
            "depth_meters": 12.085000574006699
          },
          "sample_points": [
            {
              "pixel_x": 216,
              "pixel_y": 412,
              "depth_raw": 22011,
              "depth_meters": 22.0110010454664
            },
            {
              "pixel_x": 217,
              "pixel_y": 412,
              "depth_raw": 22011,
              "depth_meters": 22.0110010454664
            },
            {
              "pixel_x": 218,
              "pixel_y": 412,
              "depth_raw": 23704,
              "depth_meters": 23.704001125879586
            },
            {
              "pixel_x": 219,
              "pixel_y": 412,
              "depth_raw": 23704,
              "depth_meters": 23.704001125879586
            },
            {
              "pixel_x": 220,
              "pixel_y": 412,
              "depth_raw": 25680,
              "depth_meters": 25.68000121973455
            },
            {
              "pixel_x": 221,
              "pixel_y": 412,
              "depth_raw": 29348,
              "depth_meters": 29.3480013939552
            },
            {
              "pixel_x": 222,
              "pixel_y": 412,
              "depth_raw": 29348,
              "depth_meters": 29.3480013939552
            },
            {
              "pixel_x": 216,
              "pixel_y": 413,
              "depth_raw": 16657,
              "depth_meters": 16.657000791165046
            },
            {
              "pixel_x": 217,
              "pixel_y": 413,
              "depth_raw": 16657,
              "depth_meters": 16.657000791165046
            },
            {
              "pixel_x": 218,
              "pixel_y": 413,
              "depth_raw": 18127,
              "depth_meters": 18.1270008609863
            },
            {
              "pixel_x": 219,
              "pixel_y": 413,
              "depth_raw": 18127,
              "depth_meters": 18.1270008609863
            },
            {
              "pixel_x": 220,
              "pixel_y": 413,
              "depth_raw": 20544,
              "depth_meters": 20.54400097578764
            },
            {
              "pixel_x": 221,
              "pixel_y": 413,
              "depth_raw": 23704,
              "depth_meters": 23.704001125879586
            },
            {
              "pixel_x": 222,
              "pixel_y": 413,
              "depth_raw": 23704,
              "depth_meters": 23.704001125879586
            },
            {
              "pixel_x": 216,
              "pixel_y": 414,
              "depth_raw": 16657,
              "depth_meters": 16.657000791165046
            },
            {
              "pixel_x": 217,
              "pixel_y": 414,
              "depth_raw": 16657,
              "depth_meters": 16.657000791165046
            },
            {
              "pixel_x": 218,
              "pixel_y": 414,
              "depth_raw": 18127,
              "depth_meters": 18.1270008609863
            },
            {
              "pixel_x": 219,
              "pixel_y": 414,
              "depth_raw": 16657,
              "depth_meters": 16.657000791165046
            },
            {
              "pixel_x": 220,
              "pixel_y": 414,
              "depth_raw": 16657,
              "depth_meters": 16.657000791165046
            },
            {
              "pixel_x": 221,
              "pixel_y": 414,
              "depth_raw": 16657,
              "depth_meters": 16.657000791165046
            },
            {
              "pixel_x": 222,
              "pixel_y": 414,
              "depth_raw": 19881,
              "depth_meters": 19.88100094429683
            },
            {
              "pixel_x": 216,
              "pixel_y": 415,
              "depth_raw": 0,
              "depth_meters": 0.0
            },
            {
              "pixel_x": 217,
              "pixel_y": 415,
              "depth_raw": 0,
              "depth_meters": 0.0
            },
            {
              "pixel_x": 218,
              "pixel_y": 415,
              "depth_raw": 0,
              "depth_meters": 0.0
            },
            {
              "pixel_x": 219,
              "pixel_y": 415,
              "depth_raw": 16657,
              "depth_meters": 16.657000791165046
            },
            {
              "pixel_x": 220,
              "pixel_y": 415,
              "depth_raw": 16657,
              "depth_meters": 16.657000791165046
            },
            {
              "pixel_x": 221,
              "pixel_y": 415,
              "depth_raw": 16657,
              "depth_meters": 16.657000791165046
            },
            {
              "pixel_x": 222,
              "pixel_y": 415,
              "depth_raw": 19881,
              "depth_meters": 19.88100094429683
            },
            {
              "pixel_x": 216,
              "pixel_y": 416,
              "depth_raw": 10813,
              "depth_meters": 10.813000513589941
            },
            {
              "pixel_x": 217,
              "pixel_y": 416,
              "depth_raw": 11006,
              "depth_meters": 11.006000522756949
            },
            {
              "pixel_x": 218,
              "pixel_y": 416,
              "depth_raw": 11006,
              "depth_meters": 11.006000522756949
            },
            {
              "pixel_x": 219,
              "pixel_y": 416,
              "depth_raw": 12085,
              "depth_meters": 12.085000574006699
            },
            {
              "pixel_x": 220,
              "pixel_y": 416,
              "depth_raw": 14007,
              "depth_meters": 14.0070006652968
            },
            {
              "pixel_x": 221,
              "pixel_y": 416,
              "depth_raw": 14007,
              "depth_meters": 14.0070006652968
            },
            {
              "pixel_x": 222,
              "pixel_y": 416,
              "depth_raw": 16657,
              "depth_meters": 16.657000791165046
            },
            {
              "pixel_x": 216,
              "pixel_y": 417,
              "depth_raw": 10813,
              "depth_meters": 10.813000513589941
            },
            {
              "pixel_x": 217,
              "pixel_y": 417,
              "depth_raw": 11006,
              "depth_meters": 11.006000522756949
            },
            {
              "pixel_x": 218,
              "pixel_y": 417,
              "depth_raw": 11006,
              "depth_meters": 11.006000522756949
            },
            {
              "pixel_x": 219,
              "pixel_y": 417,
              "depth_raw": 12085,
              "depth_meters": 12.085000574006699
            },
            {
              "pixel_x": 220,
              "pixel_y": 417,
              "depth_raw": 14007,
              "depth_meters": 14.0070006652968
            },
            {
              "pixel_x": 221,
              "pixel_y": 417,
              "depth_raw": 14007,
              "depth_meters": 14.0070006652968
            },
            {
              "pixel_x": 222,
              "pixel_y": 417,
              "depth_raw": 16657,
              "depth_meters": 16.657000791165046
            },
            {
              "pixel_x": 216,
              "pixel_y": 418,
              "depth_raw": 9199,
              "depth_meters": 9.199000436929055
            },
            {
              "pixel_x": 217,
              "pixel_y": 418,
              "depth_raw": 9338,
              "depth_meters": 9.3380004435312
            },
            {
              "pixel_x": 218,
              "pixel_y": 418,
              "depth_raw": 9338,
              "depth_meters": 9.3380004435312
            },
            {
              "pixel_x": 219,
              "pixel_y": 418,
              "depth_raw": 10272,
              "depth_meters": 10.27200048789382
            },
            {
              "pixel_x": 220,
              "pixel_y": 418,
              "depth_raw": 12085,
              "depth_meters": 12.085000574006699
            },
            {
              "pixel_x": 221,
              "pixel_y": 418,
              "depth_raw": 12085,
              "depth_meters": 12.085000574006699
            },
            {
              "pixel_x": 222,
              "pixel_y": 418,
              "depth_raw": 0,
              "depth_meters": 0.0
            },
            {
              "pixel_x": 216,
              "pixel_y": 419,
              "depth_raw": 8218,
              "depth_meters": 8.218000390334055
            },
            {
              "pixel_x": 217,
              "pixel_y": 419,
              "depth_raw": 8218,
              "depth_meters": 8.218000390334055
            },
            {
              "pixel_x": 218,
              "pixel_y": 419,
              "depth_raw": 8218,
              "depth_meters": 8.218000390334055
            },
            {
              "pixel_x": 219,
              "pixel_y": 419,
              "depth_raw": 8932,
              "depth_meters": 8.932000424247235
            },
            {
              "pixel_x": 220,
              "pixel_y": 419,
              "depth_raw": 8932,
              "depth_meters": 8.932000424247235
            },
            {
              "pixel_x": 221,
              "pixel_y": 419,
              "depth_raw": 12085,
              "depth_meters": 12.085000574006699
            },
            {
              "pixel_x": 222,
              "pixel_y": 419,
              "depth_raw": 0,
              "depth_meters": 0.0
            },
            {
              "pixel_x": 216,
              "pixel_y": 420,
              "depth_raw": 8218,
              "depth_meters": 8.218000390334055
            },
            {
              "pixel_x": 217,
              "pixel_y": 420,
              "depth_raw": 8218,
              "depth_meters": 8.218000390334055
            },
            {
              "pixel_x": 218,
              "pixel_y": 420,
              "depth_raw": 8218,
              "depth_meters": 8.218000390334055
            },
            {
              "pixel_x": 219,
              "pixel_y": 420,
              "depth_raw": 8932,
              "depth_meters": 8.932000424247235
            },
            {
              "pixel_x": 220,
              "pixel_y": 420,
              "depth_raw": 8932,
              "depth_meters": 8.932000424247235
            },
            {
              "pixel_x": 221,
              "pixel_y": 420,
              "depth_raw": 0,
              "depth_meters": 0.0
            },
            {
              "pixel_x": 222,
              "pixel_y": 420,
              "depth_raw": 0,
              "depth_meters": 0.0
            },
            {
              "pixel_x": 216,
              "pixel_y": 421,
              "depth_raw": 7901,
              "depth_meters": 7.901000375277363
            },
            {
              "pixel_x": 217,
              "pixel_y": 421,
              "depth_raw": 7801,
              "depth_meters": 7.801000370527618
            },
            {
              "pixel_x": 218,
              "pixel_y": 421,
              "depth_raw": 7801,
              "depth_meters": 7.801000370527618
            },
            {
              "pixel_x": 219,
              "pixel_y": 421,
              "depth_raw": 8443,
              "depth_meters": 8.443000401020981
            },
            {
              "pixel_x": 220,
              "pixel_y": 421,
              "depth_raw": 8443,
              "depth_meters": 8.443000401020981
            },
            {
              "pixel_x": 221,
              "pixel_y": 421,
              "depth_raw": 9941,
              "depth_meters": 9.941000472172163
            },
            {
              "pixel_x": 222,
              "pixel_y": 421,
              "depth_raw": 0,
              "depth_meters": 0.0
            }
          ],
          "depth_scale_used": 0.0010000000474974513,
          "bounding_box_depth": {
            "roi_shape": [
              10,
              7
            ],
            "mean_raw": 14409.693548387097,
            "median_raw": 13046.0
          }
        }
      }
    },
    {
      "detection_id": 5,
      "class_id": 1,
      "confidence": 0.5733551979064941,
      "bounding_box": {
        "x1": 197,
        "y1": 413,
        "x2": 204,
        "y2": 422,
        "center_x": 200,
        "center_y": 417,
        "width": 7,
        "height": 9
      },
      "relative_coordinates": {
        "rel_x": -120.0,
        "rel_y": 177.0
      },
      "depth_information": {
        "statistics": {
          "mean_depth": 46.40454387076412,
          "median_depth": 51.719002456520684,
          "min_depth": 7.901000375277363,
          "max_depth": 65.53500311274547,
          "std_depth": 17.532676275054577,
          "valid_pixels": 24,
          "total_pixels": 63,
          "fill_ratio": 0.38095238095238093
        },
        "realsense_depth_data": {
          "center_point": {
            "pixel_x": 200,
            "pixel_y": 417,
            "depth_raw": 0,
            "depth_meters": 0.0
          },
          "sample_points": [
            {
              "pixel_x": 197,
              "pixel_y": 413,
              "depth_raw": 29348,
              "depth_meters": 29.3480013939552
            },
            {
              "pixel_x": 198,
              "pixel_y": 413,
              "depth_raw": 44023,
              "depth_meters": 44.0230020909803
            },
            {
              "pixel_x": 199,
              "pixel_y": 413,
              "depth_raw": 65535,
              "depth_meters": 65.53500311274547
            },
            {
              "pixel_x": 200,
              "pixel_y": 413,
              "depth_raw": 65535,
              "depth_meters": 65.53500311274547
            },
            {
              "pixel_x": 201,
              "pixel_y": 413,
              "depth_raw": 56029,
              "depth_meters": 56.0290026612347
            },
            {
              "pixel_x": 202,
              "pixel_y": 413,
              "depth_raw": 56029,
              "depth_meters": 56.0290026612347
            },
            {
              "pixel_x": 203,
              "pixel_y": 413,
              "depth_raw": 47409,
              "depth_meters": 47.40900225180667
            },
            {
              "pixel_x": 197,
              "pixel_y": 414,
              "depth_raw": 29348,
              "depth_meters": 29.3480013939552
            },
            {
              "pixel_x": 198,
              "pixel_y": 414,
              "depth_raw": 44023,
              "depth_meters": 44.0230020909803
            },
            {
              "pixel_x": 199,
              "pixel_y": 414,
              "depth_raw": 65535,
              "depth_meters": 65.53500311274547
            },
            {
              "pixel_x": 200,
              "pixel_y": 414,
              "depth_raw": 65535,
              "depth_meters": 65.53500311274547
            },
            {
              "pixel_x": 201,
              "pixel_y": 414,
              "depth_raw": 56029,
              "depth_meters": 56.0290026612347
            },
            {
              "pixel_x": 202,
              "pixel_y": 414,
              "depth_raw": 56029,
              "depth_meters": 56.0290026612347
            },
            {
              "pixel_x": 203,
              "pixel_y": 414,
              "depth_raw": 47409,
              "depth_meters": 47.40900225180667
            },
            {
              "pixel_x": 197,
              "pixel_y": 415,
              "depth_raw": 29348,
              "depth_meters": 29.3480013939552
            },
            {
              "pixel_x": 198,
              "pixel_y": 415,
              "depth_raw": 44023,
              "depth_meters": 44.0230020909803
            },
            {
              "pixel_x": 199,
              "pixel_y": 415,
              "depth_raw": 65535,
              "depth_meters": 65.53500311274547
            },
            {
              "pixel_x": 200,
              "pixel_y": 415,
              "depth_raw": 65535,
              "depth_meters": 65.53500311274547
            },
            {
              "pixel_x": 201,
              "pixel_y": 415,
              "depth_raw": 56029,
              "depth_meters": 56.0290026612347
            },
            {
              "pixel_x": 202,
              "pixel_y": 415,
              "depth_raw": 56029,
              "depth_meters": 56.0290026612347
            },
            {
              "pixel_x": 203,
              "pixel_y": 415,
              "depth_raw": 26796,
              "depth_meters": 26.796001272741705
            },
            {
              "pixel_x": 197,
              "pixel_y": 416,
              "depth_raw": 0,
              "depth_meters": 0.0
            },
            {
              "pixel_x": 198,
              "pixel_y": 416,
              "depth_raw": 0,
              "depth_meters": 0.0
            },
            {
              "pixel_x": 199,
              "pixel_y": 416,
              "depth_raw": 0,
              "depth_meters": 0.0
            },
            {
              "pixel_x": 200,
              "pixel_y": 416,
              "depth_raw": 0,
              "depth_meters": 0.0
            },
            {
              "pixel_x": 201,
              "pixel_y": 416,
              "depth_raw": 0,
              "depth_meters": 0.0
            },
            {
              "pixel_x": 202,
              "pixel_y": 416,
              "depth_raw": 0,
              "depth_meters": 0.0
            },
            {
              "pixel_x": 203,
              "pixel_y": 416,
              "depth_raw": 26796,
              "depth_meters": 26.796001272741705
            },
            {
              "pixel_x": 197,
              "pixel_y": 417,
              "depth_raw": 0,
              "depth_meters": 0.0
            },
            {
              "pixel_x": 198,
              "pixel_y": 417,
              "depth_raw": 0,
              "depth_meters": 0.0
            },
            {
              "pixel_x": 199,
              "pixel_y": 417,
              "depth_raw": 0,
              "depth_meters": 0.0
            },
            {
              "pixel_x": 200,
              "pixel_y": 417,
              "depth_raw": 0,
              "depth_meters": 0.0
            },
            {
              "pixel_x": 201,
              "pixel_y": 417,
              "depth_raw": 0,
              "depth_meters": 0.0
            },
            {
              "pixel_x": 202,
              "pixel_y": 417,
              "depth_raw": 0,
              "depth_meters": 0.0
            },
            {
              "pixel_x": 203,
              "pixel_y": 417,
              "depth_raw": 0,
              "depth_meters": 0.0
            },
            {
              "pixel_x": 197,
              "pixel_y": 418,
              "depth_raw": 0,
              "depth_meters": 0.0
            },
            {
              "pixel_x": 198,
              "pixel_y": 418,
              "depth_raw": 0,
              "depth_meters": 0.0
            },
            {
              "pixel_x": 199,
              "pixel_y": 418,
              "depth_raw": 0,
              "depth_meters": 0.0
            },
            {
              "pixel_x": 200,
              "pixel_y": 418,
              "depth_raw": 0,
              "depth_meters": 0.0
            },
            {
              "pixel_x": 201,
              "pixel_y": 418,
              "depth_raw": 0,
              "depth_meters": 0.0
            },
            {
              "pixel_x": 202,
              "pixel_y": 418,
              "depth_raw": 0,
              "depth_meters": 0.0
            },
            {
              "pixel_x": 203,
              "pixel_y": 418,
              "depth_raw": 0,
              "depth_meters": 0.0
            },
            {
              "pixel_x": 197,
              "pixel_y": 419,
              "depth_raw": 0,
              "depth_meters": 0.0
            },
            {
              "pixel_x": 198,
              "pixel_y": 419,
              "depth_raw": 0,
              "depth_meters": 0.0
            },
            {
              "pixel_x": 199,
              "pixel_y": 419,
              "depth_raw": 0,
              "depth_meters": 0.0
            },
            {
              "pixel_x": 200,
              "pixel_y": 419,
              "depth_raw": 0,
              "depth_meters": 0.0
            },
            {
              "pixel_x": 201,
              "pixel_y": 419,
              "depth_raw": 0,
              "depth_meters": 0.0
            },
            {
              "pixel_x": 202,
              "pixel_y": 419,
              "depth_raw": 0,
              "depth_meters": 0.0
            },
            {
              "pixel_x": 203,
              "pixel_y": 419,
              "depth_raw": 0,
              "depth_meters": 0.0
            },
            {
              "pixel_x": 197,
              "pixel_y": 420,
              "depth_raw": 0,
              "depth_meters": 0.0
            },
            {
              "pixel_x": 198,
              "pixel_y": 420,
              "depth_raw": 0,
              "depth_meters": 0.0
            },
            {
              "pixel_x": 199,
              "pixel_y": 420,
              "depth_raw": 0,
              "depth_meters": 0.0
            },
            {
              "pixel_x": 200,
              "pixel_y": 420,
              "depth_raw": 0,
              "depth_meters": 0.0
            },
            {
              "pixel_x": 201,
              "pixel_y": 420,
              "depth_raw": 0,
              "depth_meters": 0.0
            },
            {
              "pixel_x": 202,
              "pixel_y": 420,
              "depth_raw": 0,
              "depth_meters": 0.0
            },
            {
              "pixel_x": 203,
              "pixel_y": 420,
              "depth_raw": 0,
              "depth_meters": 0.0
            },
            {
              "pixel_x": 197,
              "pixel_y": 421,
              "depth_raw": 7901,
              "depth_meters": 7.901000375277363
            },
            {
              "pixel_x": 198,
              "pixel_y": 421,
              "depth_raw": 7901,
              "depth_meters": 7.901000375277363
            },
            {
              "pixel_x": 199,
              "pixel_y": 421,
              "depth_raw": 0,
              "depth_meters": 0.0
            },
            {
              "pixel_x": 200,
              "pixel_y": 421,
              "depth_raw": 0,
              "depth_meters": 0.0
            },
            {
              "pixel_x": 201,
              "pixel_y": 421,
              "depth_raw": 0,
              "depth_meters": 0.0
            },
            {
              "pixel_x": 202,
              "pixel_y": 421,
              "depth_raw": 0,
              "depth_meters": 0.0
            },
            {
              "pixel_x": 203,
              "pixel_y": 421,
              "depth_raw": 0,
              "depth_meters": 0.0
            }
          ],
          "depth_scale_used": 0.0010000000474974513,
          "bounding_box_depth": {
            "roi_shape": [
              9,
              7
            ],
            "mean_raw": 46404.541666666664,
            "median_raw": 51719.0
          }
        }
      }
    },
    {
      "detection_id": 6,
      "class_id": 0,
      "confidence": 0.5658614635467529,
      "bounding_box": {
        "x1": 270,
        "y1": 411,
        "x2": 277,
        "y2": 422,
        "center_x": 273,
        "center_y": 416,
        "width": 7,
        "height": 11
      },
      "relative_coordinates": {
        "rel_x": -47.0,
        "rel_y": 176.0
      },
      "depth_information": {
        "statistics": {
          "mean_depth": 13.782956537008218,
          "median_depth": 9.199000436929055,
          "min_depth": 6.488000308163464,
          "max_depth": 38.520001829601824,
          "std_depth": 9.19055351857552,
          "valid_pixels": 68,
          "total_pixels": 77,
          "fill_ratio": 0.8831168831168831
        },
        "realsense_depth_data": {
          "center_point": {
            "pixel_x": 273,
            "pixel_y": 416,
            "depth_raw": 9199,
            "depth_meters": 9.199000436929055
          },
          "sample_points": [
            {
              "pixel_x": 270,
              "pixel_y": 411,
              "depth_raw": 38520,
              "depth_meters": 38.520001829601824
            },
            {
              "pixel_x": 271,
              "pixel_y": 411,
              "depth_raw": 36254,
              "depth_meters": 36.2540017219726
            },
            {
              "pixel_x": 272,
              "pixel_y": 411,
              "depth_raw": 36254,
              "depth_meters": 36.2540017219726
            },
            {
              "pixel_x": 273,
              "pixel_y": 411,
              "depth_raw": 38520,
              "depth_meters": 38.520001829601824
            },
            {
              "pixel_x": 274,
              "pixel_y": 411,
              "depth_raw": 36254,
              "depth_meters": 36.2540017219726
            },
            {
              "pixel_x": 275,
              "pixel_y": 411,
              "depth_raw": 36254,
              "depth_meters": 36.2540017219726
            },
            {
              "pixel_x": 276,
              "pixel_y": 411,
              "depth_raw": 36254,
              "depth_meters": 36.2540017219726
            },
            {
              "pixel_x": 270,
              "pixel_y": 412,
              "depth_raw": 19881,
              "depth_meters": 19.88100094429683
            },
            {
              "pixel_x": 271,
              "pixel_y": 412,
              "depth_raw": 19881,
              "depth_meters": 19.88100094429683
            },
            {
              "pixel_x": 272,
              "pixel_y": 412,
              "depth_raw": 19881,
              "depth_meters": 19.88100094429683
            },
            {
              "pixel_x": 273,
              "pixel_y": 412,
              "depth_raw": 20544,
              "depth_meters": 20.54400097578764
            },
            {
              "pixel_x": 274,
              "pixel_y": 412,
              "depth_raw": 20544,
              "depth_meters": 20.54400097578764
            },
            {
              "pixel_x": 275,
              "pixel_y": 412,
              "depth_raw": 21252,
              "depth_meters": 21.252001009415835
            },
            {
              "pixel_x": 276,
              "pixel_y": 412,
              "depth_raw": 21252,
              "depth_meters": 21.252001009415835
            },
            {
              "pixel_x": 270,
              "pixel_y": 413,
              "depth_raw": 14333,
              "depth_meters": 14.33300068078097
            },
            {
              "pixel_x": 271,
              "pixel_y": 413,
              "depth_raw": 14333,
              "depth_meters": 14.33300068078097
            },
            {
              "pixel_x": 272,
              "pixel_y": 413,
              "depth_raw": 19881,
              "depth_meters": 19.88100094429683
            },
            {
              "pixel_x": 273,
              "pixel_y": 413,
              "depth_raw": 20544,
              "depth_meters": 20.54400097578764
            },
            {
              "pixel_x": 274,
              "pixel_y": 413,
              "depth_raw": 20544,
              "depth_meters": 20.54400097578764
            },
            {
              "pixel_x": 275,
              "pixel_y": 413,
              "depth_raw": 21252,
              "depth_meters": 21.252001009415835
            },
            {
              "pixel_x": 276,
              "pixel_y": 413,
              "depth_raw": 21252,
              "depth_meters": 21.252001009415835
            },
            {
              "pixel_x": 270,
              "pixel_y": 414,
              "depth_raw": 14333,
              "depth_meters": 14.33300068078097
            },
            {
              "pixel_x": 271,
              "pixel_y": 414,
              "depth_raw": 14333,
              "depth_meters": 14.33300068078097
            },
            {
              "pixel_x": 272,
              "pixel_y": 414,
              "depth_raw": 0,
              "depth_meters": 0.0
            },
            {
              "pixel_x": 273,
              "pixel_y": 414,
              "depth_raw": 0,
              "depth_meters": 0.0
            },
            {
              "pixel_x": 274,
              "pixel_y": 414,
              "depth_raw": 0,
              "depth_meters": 0.0
            },
            {
              "pixel_x": 275,
              "pixel_y": 414,
              "depth_raw": 0,
              "depth_meters": 0.0
            },
            {
              "pixel_x": 276,
              "pixel_y": 414,
              "depth_raw": 0,
              "depth_meters": 0.0
            },
            {
              "pixel_x": 270,
              "pixel_y": 415,
              "depth_raw": 14333,
              "depth_meters": 14.33300068078097
            },
            {
              "pixel_x": 271,
              "pixel_y": 415,
              "depth_raw": 11006,
              "depth_meters": 11.006000522756949
            },
            {
              "pixel_x": 272,
              "pixel_y": 415,
              "depth_raw": 11006,
              "depth_meters": 11.006000522756949
            },
            {
              "pixel_x": 273,
              "pixel_y": 415,
              "depth_raw": 11006,
              "depth_meters": 11.006000522756949
            },
            {
              "pixel_x": 274,
              "pixel_y": 415,
              "depth_raw": 0,
              "depth_meters": 0.0
            },
            {
              "pixel_x": 275,
              "pixel_y": 415,
              "depth_raw": 0,
              "depth_meters": 0.0
            },
            {
              "pixel_x": 276,
              "pixel_y": 415,
              "depth_raw": 0,
              "depth_meters": 0.0
            },
            {
              "pixel_x": 270,
              "pixel_y": 416,
              "depth_raw": 0,
              "depth_meters": 0.0
            },
            {
              "pixel_x": 271,
              "pixel_y": 416,
              "depth_raw": 9199,
              "depth_meters": 9.199000436929055
            },
            {
              "pixel_x": 272,
              "pixel_y": 416,
              "depth_raw": 9199,
              "depth_meters": 9.199000436929055
            },
            {
              "pixel_x": 273,
              "pixel_y": 416,
              "depth_raw": 9199,
              "depth_meters": 9.199000436929055
            },
            {
              "pixel_x": 274,
              "pixel_y": 416,
              "depth_raw": 9199,
              "depth_meters": 9.199000436929055
            },
            {
              "pixel_x": 275,
              "pixel_y": 416,
              "depth_raw": 9199,
              "depth_meters": 9.199000436929055
            },
            {
              "pixel_x": 276,
              "pixel_y": 416,
              "depth_raw": 9199,
              "depth_meters": 9.199000436929055
            },
            {
              "pixel_x": 270,
              "pixel_y": 417,
              "depth_raw": 9338,
              "depth_meters": 9.3380004435312
            },
            {
              "pixel_x": 271,
              "pixel_y": 417,
              "depth_raw": 9199,
              "depth_meters": 9.199000436929055
            },
            {
              "pixel_x": 272,
              "pixel_y": 417,
              "depth_raw": 9199,
              "depth_meters": 9.199000436929055
            },
            {
              "pixel_x": 273,
              "pixel_y": 417,
              "depth_raw": 9199,
              "depth_meters": 9.199000436929055
            },
            {
              "pixel_x": 274,
              "pixel_y": 417,
              "depth_raw": 9199,
              "depth_meters": 9.199000436929055
            },
            {
              "pixel_x": 275,
              "pixel_y": 417,
              "depth_raw": 9199,
              "depth_meters": 9.199000436929055
            },
            {
              "pixel_x": 276,
              "pixel_y": 417,
              "depth_raw": 9199,
              "depth_meters": 9.199000436929055
            },
            {
              "pixel_x": 270,
              "pixel_y": 418,
              "depth_raw": 8218,
              "depth_meters": 8.218000390334055
            },
            {
              "pixel_x": 271,
              "pixel_y": 418,
              "depth_raw": 8218,
              "depth_meters": 8.218000390334055
            },
            {
              "pixel_x": 272,
              "pixel_y": 418,
              "depth_raw": 8004,
              "depth_meters": 8.0040003801696
            },
            {
              "pixel_x": 273,
              "pixel_y": 418,
              "depth_raw": 7901,
              "depth_meters": 7.901000375277363
            },
            {
              "pixel_x": 274,
              "pixel_y": 418,
              "depth_raw": 7901,
              "depth_meters": 7.901000375277363
            },
            {
              "pixel_x": 275,
              "pixel_y": 418,
              "depth_raw": 7901,
              "depth_meters": 7.901000375277363
            },
            {
              "pixel_x": 276,
              "pixel_y": 418,
              "depth_raw": 7901,
              "depth_meters": 7.901000375277363
            },
            {
              "pixel_x": 270,
              "pixel_y": 419,
              "depth_raw": 8218,
              "depth_meters": 8.218000390334055
            },
            {
              "pixel_x": 271,
              "pixel_y": 419,
              "depth_raw": 8218,
              "depth_meters": 8.218000390334055
            },
            {
              "pixel_x": 272,
              "pixel_y": 419,
              "depth_raw": 8004,
              "depth_meters": 8.0040003801696
            },
            {
              "pixel_x": 273,
              "pixel_y": 419,
              "depth_raw": 7901,
              "depth_meters": 7.901000375277363
            },
            {
              "pixel_x": 274,
              "pixel_y": 419,
              "depth_raw": 7901,
              "depth_meters": 7.901000375277363
            },
            {
              "pixel_x": 275,
              "pixel_y": 419,
              "depth_raw": 7901,
              "depth_meters": 7.901000375277363
            },
            {
              "pixel_x": 276,
              "pixel_y": 419,
              "depth_raw": 7901,
              "depth_meters": 7.901000375277363
            },
            {
              "pixel_x": 270,
              "pixel_y": 420,
              "depth_raw": 7251,
              "depth_meters": 7.251000344404019
            },
            {
              "pixel_x": 271,
              "pixel_y": 420,
              "depth_raw": 7251,
              "depth_meters": 7.251000344404019
            },
            {
              "pixel_x": 272,
              "pixel_y": 420,
              "depth_raw": 7084,
              "depth_meters": 7.084000336471945
            },
            {
              "pixel_x": 273,
              "pixel_y": 420,
              "depth_raw": 7004,
              "depth_meters": 7.004000332672149
            },
            {
              "pixel_x": 274,
              "pixel_y": 420,
              "depth_raw": 7004,
              "depth_meters": 7.004000332672149
            },
            {
              "pixel_x": 275,
              "pixel_y": 420,
              "depth_raw": 7004,
              "depth_meters": 7.004000332672149
            },
            {
              "pixel_x": 276,
              "pixel_y": 420,
              "depth_raw": 7004,
              "depth_meters": 7.004000332672149
            },
            {
              "pixel_x": 270,
              "pixel_y": 421,
              "depth_raw": 6773,
              "depth_meters": 6.773000321700238
            },
            {
              "pixel_x": 271,
              "pixel_y": 421,
              "depth_raw": 6773,
              "depth_meters": 6.773000321700238
            },
            {
              "pixel_x": 272,
              "pixel_y": 421,
              "depth_raw": 6557,
              "depth_meters": 6.557000311440788
            },
            {
              "pixel_x": 273,
              "pixel_y": 421,
              "depth_raw": 6557,
              "depth_meters": 6.557000311440788
            },
            {
              "pixel_x": 274,
              "pixel_y": 421,
              "depth_raw": 6488,
              "depth_meters": 6.488000308163464
            },
            {
              "pixel_x": 275,
              "pixel_y": 421,
              "depth_raw": 6488,
              "depth_meters": 6.488000308163464
            },
            {
              "pixel_x": 276,
              "pixel_y": 421,
              "depth_raw": 6488,
              "depth_meters": 6.488000308163464
            }
          ],
          "depth_scale_used": 0.0010000000474974513,
          "bounding_box_depth": {
            "roi_shape": [
              11,
              7
            ],
            "mean_raw": 13782.95588235294,
            "median_raw": 9199.0
          }
        }
      }
    }
  ]
}